Workbook
Name Portfolio_Sharpe: 'Portfolio '!$B$26
Name Portfolio_Sharpe: #REF!
Name Risk_Free_rate: Risk_Analysis!$B$13

Sheet Raw_Data
A1: GLD
A2: Date | B2: Price | C2: Open | D2: High | E2: Low | F2: Vol. | G2: Change %
A3: 46023 | B3: 421.29 | C3: 401.8 | D3: 426.84 | E3: 396.31 | F3: 156.48M | G3: 0.063
A4: 45669 | B4: 396.31 | C4: 390.61 | D4: 418.45 | E4: 382.91 | F4: 232.08M | G4: 0.0217
A5: 45668 | B5: 387.88 | C5: 368.91 | D5: 388.18 | E5: 361.39 | F5: 209.29M | G5: 0.0537
A6: 45667 | B6: 368.12 | C6: 356.17 | D6: 403.3 | E6: 351.4 | F6: 553.02M | G6: 0.0356
A7: 45666 | B7: 355.47 | C7: 320.82 | D7: 355.57 | E7: 320.24 | F7: 302.00M | G7: 0.1176
A8: 45665 | B8: 318.07 | C8: 308.61 | D8: 318.09 | E8: 305.19 | F8: 178.58M | G8: 0.0499
A9: 45664 | B9: 302.96 | C9: 308.55 | D9: 316.24 | E9: 300.95 | F9: 202.61M | G9: -0.0061
A10: 45663 | B10: 304.83 | C10: 309.21 | D10: 317.6 | E10: 299.89 | F10: 199.60M | G10: 0.0041
A11: 45662 | B11: 303.6 | C11: 297.41 | D11: 315.62 | E11: 291.78 | F11: 235.25M | G11: -0.0006
A12: 45661 | B12: 303.77 | C12: 288.54 | D12: 317.63 | E12: 272.58 | F12: 354.30M | G12: 0.0542
A13: 45660 | B13: 288.14 | C13: 265.07 | D13: 288.39 | E13: 265.07 | F13: 181.03M | G13: 0.0945
A14: 45659 | B14: 263.27 | C14: 259.75 | D14: 272.32 | E14: 259.52 | F14: 178.99M | G14: 0.0182
... A135: 42005 | B135: 123.45 | C135: 112.49 | D135: 125.58 | E135: 112.32 | F135: 198.03M | G135: 0.0869
A137: XOM
A138: Date | B138: Price | C138: Open | D138: High | E138: Low | F138: Vol. | G138: Change %
A139: 46023 | B139: 129.89 | C139: 120.05 | D139: 131.72 | E139: 118.27 | F139: 191.96M | G139: 0.0794
A140: 45669 | B140: 120.34 | C140: 116.1 | D140: 121.8 | E140: 114.61 | F140: 344.72M | G140: 0.0381
A141: 45668 | B141: 115.92 | C141: 114.5 | D141: 120.81 | E141: 112.51 | F141: 279.42M | G141: 0.0136
A142: 45667 | B142: 114.36 | C142: 112.56 | D142: 117.05 | E142: 110.39 | F142: 288.64M | G142: 0.0143
A143: 45666 | B143: 112.75 | C143: 114.18 | D143: 118.36 | E143: 108.35 | F143: 351.99M | G143: -0.0135
A144: 45665 | B144: 114.29 | C144: 112 | D144: 114.79 | E144: 105.53 | F144: 327.74M | G144: 0.0237
A145: 45664 | B145: 111.64 | C145: 108.13 | D145: 115.76 | E145: 107.15 | F145: 317.77M | G145: 0.0356
A146: 45663 | B146: 107.8 | C146: 103.75 | D146: 116.95 | E146: 101.73 | F146: 410.07M | G146: 0.0538
A147: 45662 | B147: 102.3 | C147: 105.1 | D147: 110.51 | E147: 101.18 | F147: 327.02M | G147: -0.0315
A148: 45661 | B148: 105.63 | C148: 119.22 | D148: 119.28 | E148: 97.8 | F148: 398.12M | G148: -0.1118
A149: 45660 | B149: 118.93 | C149: 111.7 | D149: 119.9 | E149: 103.67 | F149: 385.65M | G149: 0.0683
A150: 45659 | B150: 111.33 | C150: 106.64 | D150: 112.51 | E150: 105.32 | F150: 274.85M | G150: 0.0421
... A271: 42005 | B271: 87.42 | C271: 92.25 | D271: 93.05 | E271: 86.03 | F271: 326.82M | G271: -0.0544
A273: SPY
A274: Date | B274: Price | C274: Open | D274: High | E274: Low | F274: Vol. | G274: Change %
A275: 46023 | B275: 691.66 | C275: 685.64 | D275: 696.07 | E275: 679.87 | F275: 771.60M | G275: 0.0143
A276: 45669 | B276: 681.92 | C276: 678.81 | D276: 691.66 | E276: 671.2 | F276: 1.66B | G276: -0.0022
A277: 45668 | B277: 683.39 | C277: 685.67 | D277: 685.8 | E277: 650.85 | F277: 1.66B | G277: 0.002
A278: 45667 | B278: 682.06 | C278: 663.17 | D278: 689.7 | E278: 652.84 | F278: 1.78B | G278: 0.0238
A279: 45666 | B279: 666.18 | C279: 637.5 | D279: 667.34 | E279: 634.92 | F279: 1.61B | G279: 0.0328
A280: 45665 | B280: 645.05 | C280: 626.3 | D280: 649.48 | E280: 619.29 | F280: 1.42B | G280: 0.0205
A281: 45664 | B281: 632.08 | C281: 616.36 | D281: 639.85 | E281: 615.52 | F281: 1.48B | G281: 0.023
A282: 45663 | B282: 617.85 | C282: 587.76 | D282: 619.22 | E282: 585.06 | F282: 1.50B | G282: 0.0483
A283: 45662 | B283: 589.39 | C283: 560.37 | D283: 595.54 | E283: 556.04 | F283: 1.40B | G283: 0.0628
A284: 45661 | B284: 554.54 | C284: 557.45 | D284: 567.42 | E284: 481.8 | F284: 2.24B | G284: -0.0087
A285: 45660 | B285: 559.39 | C285: 596.18 | D285: 597.34 | E285: 546.87 | F285: 1.50B | G285: -0.0586
A286: 45659 | B286: 594.18 | C286: 592.67 | D286: 613.23 | E286: 582.44 | F286: 871.64M | G286: -0.0127
... A407: 42005 | B407: 199.45 | C407: 206.38 | D407: 206.88 | E407: 198.55 | F407: 3.18B | G407: -0.0296
A409: JPM
A410: Date | B410: Price | C410: Open | D410: High | E410: Low | F410: Vol. | G410: Change %
A411: 46023 | B411: 312.47 | C411: 322.27 | D411: 337.25 | E411: 306.14 | F411: 124.09M | G411: -0.0303
A412: 45669 | B412: 322.22 | C412: 312.95 | D412: 330.86 | E412: 298.46 | F412: 211.62M | G412: 0.0292
A413: 45668 | B413: 313.08 | C413: 311 | D413: 322.25 | E413: 292.81 | F413: 150.22M | G413: 0.0063
A414: 45667 | B414: 311.12 | C414: 313.97 | D414: 314.59 | E414: 290.54 | F414: 189.43M | G414: -0.0137
A415: 45666 | B415: 315.43 | C415: 300.26 | D415: 318.01 | E415: 291.44 | F415: 182.56M | G415: 0.0465
A416: 45665 | B416: 301.42 | C416: 290.4 | D416: 302.95 | E416: 284.24 | F416: 148.83M | G416: 0.0175
A417: 45664 | B417: 296.24 | C417: 290.89 | D417: 301.29 | E417: 280.31 | F417: 198.60M | G417: 0.0218
A418: 45663 | B418: 289.91 | C418: 263.02 | D418: 292.65 | E418: 260.31 | F418: 174.37M | G418: 0.0981
A419: 45662 | B419: 264 | C419: 242.84 | D419: 269.52 | E419: 242.17 | F419: 165.12M | G419: 0.0792
A420: 45661 | B420: 244.62 | C420: 242.62 | D420: 247.24 | E420: 202.16 | F420: 287.38M | G420: -0.0028
A421: 45660 | B421: 245.3 | C421: 264 | D421: 266.32 | E421: 224.23 | F421: 265.19M | G421: -0.0731
A422: 45659 | B422: 264.65 | C422: 261.83 | D422: 280.25 | E422: 253.35 | F422: 156.63M | G422: -0.0099
... A543: 42005 | B543: 54.38 | C543: 62.62 | D543: 62.96 | E543: 54.37 | F543: 468.21M | G543: -0.131
A545: NVDA
A546: Date | B546: Price | C546: Open | D546: High | E546: Low | F546: Vol. | G546: Change %
A547: 46023 | B547: 186.23 | C547: 189.71 | D547: 193.55 | E547: 180.94 | F547: 1.65B | G547: -0.0014
A548: 45669 | B548: 186.5 | C548: 174.76 | D548: 192.69 | E548: 170.31 | F548: 3.63B | G548: 0.0537
A549: 45668 | B549: 177 | C549: 208.08 | D549: 211.34 | E549: 169.55 | F549: 4.16B | G549: -0.1259
A550: 45667 | B550: 202.49 | C550: 185.24 | D550: 212.19 | E550: 176.76 | F550: 4.03B | G550: 0.0853
A551: 45666 | B551: 186.58 | C551: 170 | D551: 187.35 | E551: 164.07 | F551: 3.89B | G551: 0.0712
A552: 45665 | B552: 174.18 | C552: 174.09 | D552: 184.48 | E552: 168.8 | F552: 3.61B | G552: -0.0207
A553: 45664 | B553: 177.87 | C553: 156.29 | D553: 183.3 | E553: 151.49 | F553: 3.60B | G553: 0.1258
A554: 45663 | B554: 157.99 | C554: 135.49 | D554: 158.71 | E554: 135.4 | F554: 3.82B | G554: 0.1692
A555: 45662 | B555: 135.13 | C555: 113.08 | D555: 143.49 | E555: 110.82 | F555: 4.76B | G555: 0.2406
A556: 45661 | B556: 108.92 | C556: 108.51 | D556: 115.1 | E556: 86.62 | F556: 6.81B | G556: 0.005
A557: 45660 | B557: 108.38 | C557: 123.51 | D557: 123.7 | E557: 103.65 | F557: 6.18B | G557: -0.1324
A558: 45659 | B558: 124.92 | C558: 114.75 | D558: 143.44 | E558: 113.01 | F558: 4.76B | G558: 0.0404
... A679: 42005 | B679: 0.48 | C679: 0.5 | D679: 0.52 | E679: 0.48 | F679: 4.14B | G679: -0.0421
A683: PG
A684: Date | B684: Price | C684: Open | D684: High | E684: Low | F684: Vol. | G684: Change %
A685: 46023 | B685: 150.15 | C685: 143.12 | D685: 151.62 | E685: 137.63 | F685: 158.42M | G685: 0.0477
A686: 45669 | B686: 143.31 | C686: 148.1 | D686: 148.89 | E686: 138.14 | F686: 234.37M | G686: -0.0327
A687: 45668 | B687: 148.16 | C687: 150.1 | D687: 151.5 | E687: 144.09 | F687: 176.39M | G687: -0.0147
A688: 45667 | B688: 150.37 | C688: 153.7 | D688: 157.4 | E688: 146.96 | F688: 169.41M | G688: -0.0213
A689: 45666 | B689: 153.65 | C689: 157.36 | D689: 161.67 | E689: 150.97 | F689: 153.92M | G689: -0.0216
A690: 45665 | B690: 157.04 | C690: 151.77 | D690: 161.03 | E690: 150.02 | F690: 139.35M | G690: 0.0437
A691: 45664 | B691: 150.47 | C691: 159.88 | D691: 162.53 | E691: 149.91 | F691: 196.08M | G691: -0.0555
A692: 45663 | B692: 159.32 | C692: 169.02 | D692: 169.04 | E692: 157.17 | F692: 163.01M | G692: -0.0622
A693: 45662 | B693: 169.89 | C693: 160.65 | D693: 170.99 | E693: 156.69 | F693: 150.87M | G693: 0.045
A694: 45661 | B694: 162.57 | C694: 170.57 | D694: 174.8 | E694: 156.58 | F694: 212.13M | G694: -0.0461
A695: 45660 | B695: 170.42 | C695: 173.58 | D695: 179.99 | E695: 162.2 | F695: 182.49M | G695: -0.0197
A696: 45659 | B696: 173.84 | C696: 165.47 | D696: 174.65 | E696: 162.2 | F696: 138.22M | G696: 0.0473
... A817: 42005 | B817: 84.29 | C817: 90.84 | D817: 91.79 | E817: 84.25 | F817: 170.72M | G817: -0.0747
A821: TLT
A822: Date | B822: Price | C822: Open | D822: High | E822: Low | F822: Vol. | G822: Change %
A823: 46023 | B823: 87.63 | C823: 87.4 | D823: 88.66 | E823: 86.55 | F823: 571.80M | G823: 0.0054
A824: 45669 | B824: 87.16 | C824: 88.85 | D824: 89.15 | E824: 87.03 | F824: 708.84M | G824: -0.0338
A825: 45668 | B825: 90.21 | C825: 89.62 | D825: 90.64 | E825: 88.8 | F825: 612.76M | G825: -0.0009
A826: 45667 | B826: 90.29 | C826: 89.45 | D826: 92.18 | E826: 88.65 | F826: 732.52M | G826: 0.0103
A827: 45666 | B827: 89.37 | C827: 85.63 | D827: 91.04 | E827: 85.48 | F827: 823.69M | G827: 0.032
A828: 45665 | B828: 86.6 | C828: 87.56 | D828: 88.45 | E828: 85.99 | F828: 712.88M | G828: -0.0037
A829: 45664 | B829: 86.92 | C829: 88.13 | D829: 88.31 | E829: 84.19 | F829: 784.07M | G829: -0.0151
A830: 45663 | B830: 88.25 | C830: 85.29 | D830: 88.43 | E830: 84.79 | F830: 784.30M | G830: 0.0228
...

Sheet Clean_Data
A1: GLD
A2: Date | B2: Price
A3: 46023 | B3: 421.29
A4: 45992 | B4: 396.31
A5: 45962 | B5: 387.88
A6: 45931 | B6: 368.12
A7: 45901 | B7: 355.47
A8: 45870 | B8: 318.07
A9: 45839 | B9: 302.96
A10: 45809 | B10: 304.83
A11: 45778 | B11: 303.6
A12: 45748 | B12: 303.77
A13: 45717 | B13: 288.14
A14: 45689 | B14: 263.27
... A135: 42005 | B135: 123.45
A138: XOM
A139: Date | B139: Price
A140: 46023 | B140: 129.89
A141: 45992 | B141: 120.34 | D141: =MONTH(Table3[[#This Row],[Date]]) -> 12
A142: 45962 | B142: 115.92
A143: 45931 | B143: 114.36
A144: 45901 | B144: 112.75
A145: 45870 | B145: 114.29
A146: 45839 | B146: 111.64
A147: 45809 | B147: 107.8
A148: 45778 | B148: 102.3
A149: 45748 | B149: 105.63
A150: 45717 | B150: 118.93
A151: 45689 | B151: 111.33
A152: 45658 | B152: 106.83
A153: 45627 | B153: 107.57
... A272: 42005 | B272: 87.42
A275: SPY
A276: Date | B276: Price
A277: 46023 | B277: 691.66
A278: 45992 | B278: 681.92 | D278: =MONTH(Table4[[#This Row],[Date]]) -> 12
A279: 45962 | B279: 683.39
A280: 45931 | B280: 682.06
A281: 45901 | B281: 666.18
A282: 45870 | B282: 645.05
A283: 45839 | B283: 632.08
A284: 45809 | B284: 617.85
A285: 45778 | B285: 589.39
A286: 45748 | B286: 554.54
A287: 45717 | B287: 559.39
A288: 45689 | B288: 594.18
A289: 45658 | B289: 601.82
A290: 45627 | B290: 586.08
... A409: 42005 | B409: 199.45
A412: JPM
A413: Date | B413: Price
A414: 46023 | B414: 312.47
A415: 45992 | B415: 322.22 | D415: =MONTH(Table5[[#This Row],[Date]]) -> 12
A416: 45962 | B416: 313.08
A417: 45931 | B417: 311.12
A418: 45901 | B418: 315.43
A419: 45870 | B419: 301.42
A420: 45839 | B420: 296.24
A421: 45809 | B421: 289.91
A422: 45778 | B422: 264
A423: 45748 | B423: 244.62
A424: 45717 | B424: 245.3
A425: 45689 | B425: 264.65
A426: 45658 | B426: 267.3
A427: 45627 | B427: 239.71
... A546: 42005 | B546: 54.38
A550: NVDA
A551: Date | B551: Price
A552: 46023 | B552: 186.23
A553: 45992 | B553: 186.5 | D553: =MONTH(Table6[[#This Row],[Date]]) -> 12
A554: 45962 | B554: 177
A555: 45931 | B555: 202.49
A556: 45901 | B556: 186.58
A557: 45870 | B557: 174.18
A558: 45839 | B558: 177.87
A559: 45809 | B559: 157.99
A560: 45778 | B560: 135.13
A561: 45748 | B561: 108.92
A562: 45717 | B562: 108.38
A563: 45689 | B563: 124.92
A564: 45658 | B564: 120.07
A565: 45627 | B565: 134.29
... A684: 42005 | B684: 0.48
A687: PG
A688: Date | B688: PG | C688: Date_Fixed
A689: 46023 | B689: 150.15 | C689: =DATE(YEAR(A689),DAY(A689),MONTH(A689)) -> 46023
A690: 45992 | B690: 143.31 | C690: =DATE(YEAR(A690),DAY(A690),MONTH(A690)) -> 45669 | E690: =MONTH(PG[[#This Row],[Date]]) -> 12
A691: 45962 | B691: 148.16 | C691: =DATE(YEAR(A691),DAY(A691),MONTH(A691)) -> 45668
A692: 45931 | B692: 150.37 | C692: =DATE(YEAR(A692),DAY(A692),MONTH(A692)) -> 45667
A693: 45901 | B693: 153.65 | C693: =DATE(YEAR(A693),DAY(A693),MONTH(A693)) -> 45666
A694: 45870 | B694: 157.04 | C694: =DATE(YEAR(A694),DAY(A694),MONTH(A694)) -> 45665
A695: 45839 | B695: 150.47 | C695: =DATE(YEAR(A695),DAY(A695),MONTH(A695)) -> 45664
A696: 45809 | B696: 159.32 | C696: =DATE(YEAR(A696),DAY(A696),MONTH(A696)) -> 45663
A697: 45778 | B697: 169.89 | C697: =DATE(YEAR(A697),DAY(A697),MONTH(A697)) -> 45662
A698: 45748 | B698: 162.57 | C698: =DATE(YEAR(A698),DAY(A698),MONTH(A698)) -> 45661
A699: 45717 | B699: 170.42 | C699: =DATE(YEAR(A699),DAY(A699),MONTH(A699)) -> 45660
A700: 45689 | B700: 173.84 | C700: =DATE(YEAR(A700),DAY(A700),MONTH(A700)) -> 45659
A701: 45658 | B701: 165.99 | C701: =DATE(YEAR(A701),DAY(A701),MONTH(A701)) -> 45658
A702: 45627 | B702: 167.65 | C702: =DATE(YEAR(A702),DAY(A702),MONTH(A702)) -> 45303
... A821: 42005 | B821: 84.29 | C821: =DATE(YEAR(A821),DAY(A821),MONTH(A821)) -> 42005
...

Sheet Assumptions
B3: Parameter | C3: Value
B4: Risk-Free Rate (Annual) | C4: 0.04
B5: Risk-Free Rate (Monthly) | C5: =(1+C4)^(1/12)-1 -> 0.0032737398
B6: Return Frequency | C6: Monthly
B7: Return Type | C7: Simple
B8: Benchmark (Market) | C8: SPY
B9: Sample Start | C9: 42005
B10: Sample End | C10: 46023
B11: VaR Method | C11: Historical
B12: VaR Confidence Levels | C12: 90%, 95%, 99%

Sheet TimeLine
A1: Date | B1: GLD | C1: XOM | D1: SPY | E1: JPM | F1: NVDA | G1: PG | H1: TLT | I1: VGT | J1: VNQ | K1: VXUS
A2: 42005 | B2: =INDEX(Table2[Price],MATCH(TimeLine!A2,Table2[Date],0)) -> 123.45 | C2: =INDEX(Table3[Price],MATCH(TimeLine!A2,Table3[Date],0)) -> 87.42 | D2: =INDEX(Table4[Price],MATCH(TimeLine!A2,Table4[Date],0)) -> 199.45 | E2: =INDEX(Table5[Price],MATCH(TimeLine!A2,Table5[Date],0)) -> 54.38 | F2: =INDEX(Table6[Price],MATCH(TimeLine!A2,Table6[Date],0)) -> 0.48 | G2: =INDEX(PG[PG],MATCH(Table_RawData[[#This Row],[Date]],PG[Date],0)) -> 84.29 | H2: =INDEX(TLT[TLT],MATCH(Table_RawData[[#This Row],[Date]],TLT[Date],0)) -> 138.28 | I2: =INDEX(VGT[VGT],MATCH(Table_RawData[[#This Row],[Date]],VGT[Date],0)) -> 100.81 | J2: =INDEX(VNQ[VNQ],MATCH(Table_RawData[[#This Row],[Date]],VNQ[Date],0)) -> 86.55 | K2: =INDEX(VXUS[VXUS],MATCH(Table_RawData[[#This Row],[Date]],VXUS[Date],0)) -> 48.47
A3: =EDATE(A2,1) -> 42036 | B3: =INDEX(Table2[Price],MATCH(TimeLine!A3,Table2[Date],0)) -> 116.16 | C3: =INDEX(Table3[Price],MATCH(TimeLine!A3,Table3[Date],0)) -> 88.54 | D3: =INDEX(Table4[Price],MATCH(TimeLine!A3,Table4[Date],0)) -> 210.66 | E3: =INDEX(Table5[Price],MATCH(TimeLine!A3,Table5[Date],0)) -> 61.28 | F3: =INDEX(Table6[Price],MATCH(TimeLine!A3,Table6[Date],0)) -> 0.55 | G3: =INDEX(PG[PG],MATCH(Table_RawData[[#This Row],[Date]],PG[Date],0)) -> 85.13 | H3: =INDEX(TLT[TLT],MATCH(Table_RawData[[#This Row],[Date]],TLT[Date],0)) -> 129.53 | I3: =INDEX(VGT[VGT],MATCH(Table_RawData[[#This Row],[Date]],VGT[Date],0)) -> 109.21 | J3: =INDEX(VNQ[VNQ],MATCH(Table_RawData[[#This Row],[Date]],VNQ[Date],0)) -> 83.37 | K3: =INDEX(VXUS[VXUS],MATCH(Table_RawData[[#This Row],[Date]],VXUS[Date],0)) -> 51.27
A4: =EDATE(A3,1) -> 42064 | B4: =INDEX(Table2[Price],MATCH(TimeLine!A4,Table2[Date],0)) -> 113.66 | C4: =INDEX(Table3[Price],MATCH(TimeLine!A4,Table3[Date],0)) -> 85 | D4: =INDEX(Table4[Price],MATCH(TimeLine!A4,Table4[Date],0)) -> 206.43 | E4: =INDEX(Table5[Price],MATCH(TimeLine!A4,Table5[Date],0)) -> 60.58 | F4: =INDEX(Table6[Price],MATCH(TimeLine!A4,Table6[Date],0)) -> 0.52 | G4: =INDEX(PG[PG],MATCH(Table_RawData[[#This Row],[Date]],PG[Date],0)) -> 81.94 | H4: =INDEX(TLT[TLT],MATCH(Table_RawData[[#This Row],[Date]],TLT[Date],0)) -> 130.69 | I4: =INDEX(VGT[VGT],MATCH(Table_RawData[[#This Row],[Date]],VGT[Date],0)) -> 106.52 | J4: =INDEX(VNQ[VNQ],MATCH(Table_RawData[[#This Row],[Date]],VNQ[Date],0)) -> 84.31 | K4: =INDEX(VXUS[VXUS],MATCH(Table_RawData[[#This Row],[Date]],VXUS[Date],0)) -> 50.35
A5: =EDATE(A4,1) -> 42095 | B5: =INDEX(Table2[Price],MATCH(TimeLine!A5,Table2[Date],0)) -> 113.47 | C5: =INDEX(Table3[Price],MATCH(TimeLine!A5,Table3[Date],0)) -> 87.37 | D5: =INDEX(Table4[Price],MATCH(TimeLine!A5,Table4[Date],0)) -> 208.46 | E5: =INDEX(Table5[Price],MATCH(TimeLine!A5,Table5[Date],0)) -> 63.26 | F5: =INDEX(Table6[Price],MATCH(TimeLine!A5,Table6[Date],0)) -> 0.55 | G5: =INDEX(PG[PG],MATCH(Table_RawData[[#This Row],[Date]],PG[Date],0)) -> 79.51 | H5: =INDEX(TLT[TLT],MATCH(Table_RawData[[#This Row],[Date]],TLT[Date],0)) -> 125.95 | I5: =INDEX(VGT[VGT],MATCH(Table_RawData[[#This Row],[Date]],VGT[Date],0)) -> 107.89 | J5: =INDEX(VNQ[VNQ],MATCH(Table_RawData[[#This Row],[Date]],VNQ[Date],0)) -> 79.38 | K5: =INDEX(VXUS[VXUS],MATCH(Table_RawData[[#This Row],[Date]],VXUS[Date],0)) -> 52.77
A6: =EDATE(A5,1) -> 42125 | B6: =INDEX(Table2[Price],MATCH(TimeLine!A6,Table2[Date],0)) -> 114.1 | C6: =INDEX(Table3[Price],MATCH(TimeLine!A6,Table3[Date],0)) -> 85.2 | D6: =INDEX(Table4[Price],MATCH(TimeLine!A6,Table4[Date],0)) -> 211.14 | E6: =INDEX(Table5[Price],MATCH(TimeLine!A6,Table5[Date],0)) -> 65.78 | F6: =INDEX(Table6[Price],MATCH(TimeLine!A6,Table6[Date],0)) -> 0.55 | G6: =INDEX(PG[PG],MATCH(Table_RawData[[#This Row],[Date]],PG[Date],0)) -> 78.39 | H6: =INDEX(TLT[TLT],MATCH(Table_RawData[[#This Row],[Date]],TLT[Date],0)) -> 122.71 | I6: =INDEX(VGT[VGT],MATCH(Table_RawData[[#This Row],[Date]],VGT[Date],0)) -> 110.58 | J6: =INDEX(VNQ[VNQ],MATCH(Table_RawData[[#This Row],[Date]],VNQ[Date],0)) -> 79.14 | K6: =INDEX(VXUS[VXUS],MATCH(Table_RawData[[#This Row],[Date]],VXUS[Date],0)) -> 52.29
A7: =EDATE(A6,1) -> 42156 | B7: =INDEX(Table2[Price],MATCH(TimeLine!A7,Table2[Date],0)) -> 112.37 | C7: =INDEX(Table3[Price],MATCH(TimeLine!A7,Table3[Date],0)) -> 83.2 | D7: =INDEX(Table4[Price],MATCH(TimeLine!A7,Table4[Date],0)) -> 205.85 | E7: =INDEX(Table5[Price],MATCH(TimeLine!A7,Table5[Date],0)) -> 67.76 | F7: =INDEX(Table6[Price],MATCH(TimeLine!A7,Table6[Date],0)) -> 0.5 | G7: =INDEX(PG[PG],MATCH(Table_RawData[[#This Row],[Date]],PG[Date],0)) -> 78.24 | H7: =INDEX(TLT[TLT],MATCH(Table_RawData[[#This Row],[Date]],TLT[Date],0)) -> 117.46 | I7: =INDEX(VGT[VGT],MATCH(Table_RawData[[#This Row],[Date]],VGT[Date],0)) -> 106.23 | J7: =INDEX(VNQ[VNQ],MATCH(Table_RawData[[#This Row],[Date]],VNQ[Date],0)) -> 74.69 | K7: =INDEX(VXUS[VXUS],MATCH(Table_RawData[[#This Row],[Date]],VXUS[Date],0)) -> 50.33
A8: =EDATE(A7,1) -> 42186 | B8: =INDEX(Table2[Price],MATCH(TimeLine!A8,Table2[Date],0)) -> 104.93 | C8: =INDEX(Table3[Price],MATCH(TimeLine!A8,Table3[Date],0)) -> 79.21 | D8: =INDEX(Table4[Price],MATCH(TimeLine!A8,Table4[Date],0)) -> 210.5 | E8: =INDEX(Table5[Price],MATCH(TimeLine!A8,Table5[Date],0)) -> 68.53 | F8: =INDEX(Table6[Price],MATCH(TimeLine!A8,Table6[Date],0)) -> 0.5 | G8: =INDEX(PG[PG],MATCH(Table_RawData[[#This Row],[Date]],PG[Date],0)) -> 76.7 | H8: =INDEX(TLT[TLT],MATCH(Table_RawData[[#This Row],[Date]],TLT[Date],0)) -> 122.53 | I8: =INDEX(VGT[VGT],MATCH(Table_RawData[[#This Row],[Date]],VGT[Date],0)) -> 108.64 | J8: =INDEX(VNQ[VNQ],MATCH(Table_RawData[[#This Row],[Date]],VNQ[Date],0)) -> 79 | K8: =INDEX(VXUS[VXUS],MATCH(Table_RawData[[#This Row],[Date]],VXUS[Date],0)) -> 50.05
A9: =EDATE(A8,1) -> 42217 | B9: =INDEX(Table2[Price],MATCH(TimeLine!A9,Table2[Date],0)) -> 108.82 | C9: =INDEX(Table3[Price],MATCH(TimeLine!A9,Table3[Date],0)) -> 75.24 | D9: =INDEX(Table4[Price],MATCH(TimeLine!A9,Table4[Date],0)) -> 197.67 | E9: =INDEX(Table5[Price],MATCH(TimeLine!A9,Table5[Date],0)) -> 64.1 | F9: =INDEX(Table6[Price],MATCH(TimeLine!A9,Table6[Date],0)) -> 0.56 | G9: =INDEX(PG[PG],MATCH(Table_RawData[[#This Row],[Date]],PG[Date],0)) -> 70.67 | H9: =INDEX(TLT[TLT],MATCH(Table_RawData[[#This Row],[Date]],TLT[Date],0)) -> 121.42 | I9: =INDEX(VGT[VGT],MATCH(Table_RawData[[#This Row],[Date]],VGT[Date],0)) -> 102.34 | J9: =INDEX(VNQ[VNQ],MATCH(Table_RawData[[#This Row],[Date]],VNQ[Date],0)) -> 74.03 | K9: =INDEX(VXUS[VXUS],MATCH(Table_RawData[[#This Row],[Date]],VXUS[Date],0)) -> 46.33
A10: =EDATE(A9,1) -> 42248 | B10: =INDEX(Table2[Price],MATCH(TimeLine!A10,Table2[Date],0)) -> 106.86 | C10: =INDEX(Table3[Price],MATCH(TimeLine!A10,Table3[Date],0)) -> 74.35 | D10: =INDEX(Table4[Price],MATCH(TimeLine!A10,Table4[Date],0)) -> 191.63 | E10: =INDEX(Table5[Price],MATCH(TimeLine!A10,Table5[Date],0)) -> 60.97 | F10: =INDEX(Table6[Price],MATCH(TimeLine!A10,Table6[Date],0)) -> 0.62 | G10: =INDEX(PG[PG],MATCH(Table_RawData[[#This Row],[Date]],PG[Date],0)) -> 71.94 | H10: =INDEX(TLT[TLT],MATCH(Table_RawData[[#This Row],[Date]],TLT[Date],0)) -> 123.54 | I10: =INDEX(VGT[VGT],MATCH(Table_RawData[[#This Row],[Date]],VGT[Date],0)) -> 100 | J10: =INDEX(VNQ[VNQ],MATCH(Table_RawData[[#This Row],[Date]],VNQ[Date],0)) -> 75.54 | K10: =INDEX(VXUS[VXUS],MATCH(Table_RawData[[#This Row],[Date]],VXUS[Date],0)) -> 44.32
A11: =EDATE(A10,1) -> 42278 | B11: =INDEX(Table2[Price],MATCH(TimeLine!A11,Table2[Date],0)) -> 109.3 | C11: =INDEX(Table3[Price],MATCH(TimeLine!A11,Table3[Date],0)) -> 82.74 | D11: =INDEX(Table4[Price],MATCH(TimeLine!A11,Table4[Date],0)) -> 207.93 | E11: =INDEX(Table5[Price],MATCH(TimeLine!A11,Table5[Date],0)) -> 64.25 | F11: =INDEX(Table6[Price],MATCH(TimeLine!A11,Table6[Date],0)) -> 0.71 | G11: =INDEX(PG[PG],MATCH(Table_RawData[[#This Row],[Date]],PG[Date],0)) -> 76.38 | H11: =INDEX(TLT[TLT],MATCH(Table_RawData[[#This Row],[Date]],TLT[Date],0)) -> 122.78 | I11: =INDEX(VGT[VGT],MATCH(Table_RawData[[#This Row],[Date]],VGT[Date],0)) -> 110.46 | J11: =INDEX(VNQ[VNQ],MATCH(Table_RawData[[#This Row],[Date]],VNQ[Date],0)) -> 79.89 | K11: =INDEX(VXUS[VXUS],MATCH(Table_RawData[[#This Row],[Date]],VXUS[Date],0)) -> 47.09
A12: =EDATE(A11,1) -> 42309 | B12: =INDEX(Table2[Price],MATCH(TimeLine!A12,Table2[Date],0)) -> 101.92 | C12: =INDEX(Table3[Price],MATCH(TimeLine!A12,Table3[Date],0)) -> 81.66 | D12: =INDEX(Table4[Price],MATCH(TimeLine!A12,Table4[Date],0)) -> 208.69 | E12: =INDEX(Table5[Price],MATCH(TimeLine!A12,Table5[Date],0)) -> 66.68 | F12: =INDEX(Table6[Price],MATCH(TimeLine!A12,Table6[Date],0)) -> 0.79 | G12: =INDEX(PG[PG],MATCH(Table_RawData[[#This Row],[Date]],PG[Date],0)) -> 74.84 | H12: =INDEX(TLT[TLT],MATCH(Table_RawData[[#This Row],[Date]],TLT[Date],0)) -> 121.45 | I12: =INDEX(VGT[VGT],MATCH(Table_RawData[[#This Row],[Date]],VGT[Date],0)) -> 111.77 | J12: =INDEX(VNQ[VNQ],MATCH(Table_RawData[[#This Row],[Date]],VNQ[Date],0)) -> 79.39 | K12: =INDEX(VXUS[VXUS],MATCH(Table_RawData[[#This Row],[Date]],VXUS[Date],0)) -> 46.47
A13: =EDATE(A12,1) -> 42339 | B13: =INDEX(Table2[Price],MATCH(TimeLine!A13,Table2[Date],0)) -> 101.46 | C13: =INDEX(Table3[Price],MATCH(TimeLine!A13,Table3[Date],0)) -> 77.95 | D13: =INDEX(Table4[Price],MATCH(TimeLine!A13,Table4[Date],0)) -> 203.87 | E13: =INDEX(Table5[Price],MATCH(TimeLine!A13,Table5[Date],0)) -> 66.03 | F13: =INDEX(Table6[Price],MATCH(TimeLine!A13,Table6[Date],0)) -> 0.82 | G13: =INDEX(PG[PG],MATCH(Table_RawData[[#This Row],[Date]],PG[Date],0)) -> 79.41 | H13: =INDEX(TLT[TLT],MATCH(Table_RawData[[#This Row],[Date]],TLT[Date],0)) -> 120.58 | I13: =INDEX(VGT[VGT],MATCH(Table_RawData[[#This Row],[Date]],VGT[Date],0)) -> 108.29 | J13: =INDEX(VNQ[VNQ],MATCH(Table_RawData[[#This Row],[Date]],VNQ[Date],0)) -> 79.73 | K13: =INDEX(VXUS[VXUS],MATCH(Table_RawData[[#This Row],[Date]],VXUS[Date],0)) -> 45.11
A14: =EDATE(A13,1) -> 42370 | B14: =INDEX(Table2[Price],MATCH(TimeLine!A14,Table2[Date],0)) -> 106.95 | C14: =INDEX(Table3[Price],MATCH(TimeLine!A14,Table3[Date],0)) -> 77.85 | D14: =INDEX(Table4[Price],MATCH(TimeLine!A14,Table4[Date],0)) -> 193.72 | E14: =INDEX(Table5[Price],MATCH(TimeLine!A14,Table5[Date],0)) -> 59.5 | F14: =INDEX(Table6[Price],MATCH(TimeLine!A14,Table6[Date],0)) -> 0.73 | G14: =INDEX(PG[PG],MATCH(Table_RawData[[#This Row],[Date]],PG[Date],0)) -> 81.69 | H14: =INDEX(TLT[TLT],MATCH(Table_RawData[[#This Row],[Date]],TLT[Date],0)) -> 127.3 | I14: =INDEX(VGT[VGT],MATCH(Table_RawData[[#This Row],[Date]],VGT[Date],0)) -> 101.93 | J14: =INDEX(VNQ[VNQ],MATCH(Table_RawData[[#This Row],[Date]],VNQ[Date],0)) -> 76.99 | K14: =INDEX(VXUS[VXUS],MATCH(Table_RawData[[#This Row],[Date]],VXUS[Date],0)) -> 42.65
... A134: =EDATE(A133,1) -> 46023 | B134: =INDEX(Table2[Price],MATCH(TimeLine!A134,Table2[Date],0)) -> 421.29 | C134: =INDEX(Table3[Price],MATCH(TimeLine!A134,Table3[Date],0)) -> 129.89 | D134: =INDEX(Table4[Price],MATCH(TimeLine!A134,Table4[Date],0)) -> 691.66 | E134: =INDEX(Table5[Price],MATCH(TimeLine!A134,Table5[Date],0)) -> 312.47 | F134: =INDEX(Table6[Price],MATCH(TimeLine!A134,Table6[Date],0)) -> 186.23 | G134: =INDEX(PG[PG],MATCH(Table_RawData[[#This Row],[Date]],PG[Date],0)) -> 150.15 | H134: =INDEX(TLT[TLT],MATCH(Table_RawData[[#This Row],[Date]],TLT[Date],0)) -> 87.63 | I134: =INDEX(VGT[VGT],MATCH(Table_RawData[[#This Row],[Date]],VGT[Date],0)) -> 753.57 | J134: =INDEX(VNQ[VNQ],MATCH(Table_RawData[[#This Row],[Date]],VNQ[Date],0)) -> 90.37 | K134: =INDEX(VXUS[VXUS],MATCH(Table_RawData[[#This Row],[Date]],VXUS[Date],0)) -> 79.53
A135: Total | B135: =COUNT(Table_RawData[GLD]) -> 133 | C135: =COUNT(Table_RawData[XOM]) -> 133 | D135: =COUNT(Table_RawData[SPY]) -> 133 | E135: =COUNT(Table_RawData[JPM]) -> 133 | F135: =COUNT(Table_RawData[NVDA]) -> 133 | G135: =COUNT(Table_RawData[PG]) -> 133 | H135: =COUNT(Table_RawData[TLT]) -> 133 | I135: =COUNT(Table_RawData[VGT]) -> 133 | J135: =COUNT(Table_RawData[VNQ]) -> 133 | K135: =COUNT(Table_RawData[VXUS]) -> 133

Sheet Returns
A1: Monthly Returns
A2: Date | B2: GLD | C2: XOM | D2: SPY | E2: JPM | F2: NVDA | G2: PG | H2: TLT | I2: VGT | J2: VNQ | K2: VXUS
A3: =TimeLine!A3 -> 42036 | B3: =IFERROR((TimeLine!B3/TimeLine!B2)-1, NA()) -> -0.059052248 | C3: =IFERROR((TimeLine!C3/TimeLine!C2)-1, NA()) -> 0.012811714 | D3: =IFERROR((TimeLine!D3/TimeLine!D2)-1, NA()) -> 0.056204563 | E3: =IFERROR((TimeLine!E3/TimeLine!E2)-1, NA()) -> 0.12688488 | F3: =IFERROR((TimeLine!F3/TimeLine!F2)-1, NA()) -> 0.14583333 | G3: =IFERROR((TimeLine!G3/TimeLine!G2)-1, NA()) -> 0.009965595 | H3: =IFERROR((TimeLine!H3/TimeLine!H2)-1, NA()) -> -0.063277408 | I3: =IFERROR((TimeLine!I3/TimeLine!I2)-1, NA()) -> 0.083325067 | ... K3: =IFERROR((TimeLine!K3/TimeLine!K2)-1, NA()) -> 0.057767691
A4: =TimeLine!A4 -> 42064 | B4: =IFERROR((TimeLine!B4/TimeLine!B3)-1, NA()) -> -0.021522039 | C4: =IFERROR((TimeLine!C4/TimeLine!C3)-1, NA()) -> -0.039981929 | D4: =IFERROR((TimeLine!D4/TimeLine!D3)-1, NA()) -> -0.020079749 | E4: =IFERROR((TimeLine!E4/TimeLine!E3)-1, NA()) -> -0.011422977 | F4: =IFERROR((TimeLine!F4/TimeLine!F3)-1, NA()) -> -0.054545455 | G4: =IFERROR((TimeLine!G4/TimeLine!G3)-1, NA()) -> -0.037472101 | H4: =IFERROR((TimeLine!H4/TimeLine!H3)-1, NA()) -> 0.0089554543 | I4: =IFERROR((TimeLine!I4/TimeLine!I3)-1, NA()) -> -0.024631444 | ... K4: =IFERROR((TimeLine!K4/TimeLine!K3)-1, NA()) -> -0.017944217
A5: =TimeLine!A5 -> 42095 | B5: =IFERROR((TimeLine!B5/TimeLine!B4)-1, NA()) -> -0.0016716523 | C5: =IFERROR((TimeLine!C5/TimeLine!C4)-1, NA()) -> 0.027882353 | D5: =IFERROR((TimeLine!D5/TimeLine!D4)-1, NA()) -> 0.009833842 | E5: =IFERROR((TimeLine!E5/TimeLine!E4)-1, NA()) -> 0.044239023 | F5: =IFERROR((TimeLine!F5/TimeLine!F4)-1, NA()) -> 0.057692308 | G5: =IFERROR((TimeLine!G5/TimeLine!G4)-1, NA()) -> -0.029655846 | H5: =IFERROR((TimeLine!H5/TimeLine!H4)-1, NA()) -> -0.036269034 | I5: =IFERROR((TimeLine!I5/TimeLine!I4)-1, NA()) -> 0.012861434 | ... K5: =IFERROR((TimeLine!K5/TimeLine!K4)-1, NA()) -> 0.048063555
A6: =TimeLine!A6 -> 42125 | B6: =IFERROR((TimeLine!B6/TimeLine!B5)-1, NA()) -> 0.0055521283 | C6: =IFERROR((TimeLine!C6/TimeLine!C5)-1, NA()) -> -0.024836901 | D6: =IFERROR((TimeLine!D6/TimeLine!D5)-1, NA()) -> 0.012856183 | E6: =IFERROR((TimeLine!E6/TimeLine!E5)-1, NA()) -> 0.039835599 | F6: =IFERROR((TimeLine!F6/TimeLine!F5)-1, NA()) -> 0 | G6: =IFERROR((TimeLine!G6/TimeLine!G5)-1, NA()) -> -0.014086278 | H6: =IFERROR((TimeLine!H6/TimeLine!H5)-1, NA()) -> -0.025724494 | I6: =IFERROR((TimeLine!I6/TimeLine!I5)-1, NA()) -> 0.024932802 | ... K6: =IFERROR((TimeLine!K6/TimeLine!K5)-1, NA()) -> -0.0090960773
A7: =TimeLine!A7 -> 42156 | B7: =IFERROR((TimeLine!B7/TimeLine!B6)-1, NA()) -> -0.015162138 | C7: =IFERROR((TimeLine!C7/TimeLine!C6)-1, NA()) -> -0.023474178 | D7: =IFERROR((TimeLine!D7/TimeLine!D6)-1, NA()) -> -0.025054466 | E7: =IFERROR((TimeLine!E7/TimeLine!E6)-1, NA()) -> 0.030100334 | F7: =IFERROR((TimeLine!F7/TimeLine!F6)-1, NA()) -> -0.090909091 | G7: =IFERROR((TimeLine!G7/TimeLine!G6)-1, NA()) -> -0.0019135094 | H7: =IFERROR((TimeLine!H7/TimeLine!H6)-1, NA()) -> -0.042783799 | I7: =IFERROR((TimeLine!I7/TimeLine!I6)-1, NA()) -> -0.039338036 | ... K7: =IFERROR((TimeLine!K7/TimeLine!K6)-1, NA()) -> -0.037483266
A8: =TimeLine!A8 -> 42186 | B8: =IFERROR((TimeLine!B8/TimeLine!B7)-1, NA()) -> -0.066209842 | C8: =IFERROR((TimeLine!C8/TimeLine!C7)-1, NA()) -> -0.047956731 | D8: =IFERROR((TimeLine!D8/TimeLine!D7)-1, NA()) -> 0.022589264 | E8: =IFERROR((TimeLine!E8/TimeLine!E7)-1, NA()) -> 0.011363636 | F8: =IFERROR((TimeLine!F8/TimeLine!F7)-1, NA()) -> 0 | G8: =IFERROR((TimeLine!G8/TimeLine!G7)-1, NA()) -> -0.019683027 | H8: =IFERROR((TimeLine!H8/TimeLine!H7)-1, NA()) -> 0.04316363 | I8: =IFERROR((TimeLine!I8/TimeLine!I7)-1, NA()) -> 0.022686623 | ... K8: =IFERROR((TimeLine!K8/TimeLine!K7)-1, NA()) -> -0.0055632823
A9: =TimeLine!A9 -> 42217 | B9: =IFERROR((TimeLine!B9/TimeLine!B8)-1, NA()) -> 0.037072334 | C9: =IFERROR((TimeLine!C9/TimeLine!C8)-1, NA()) -> -0.050119934 | D9: =IFERROR((TimeLine!D9/TimeLine!D8)-1, NA()) -> -0.060950119 | E9: =IFERROR((TimeLine!E9/TimeLine!E8)-1, NA()) -> -0.064643222 | F9: =IFERROR((TimeLine!F9/TimeLine!F8)-1, NA()) -> 0.12 | G9: =IFERROR((TimeLine!G9/TimeLine!G8)-1, NA()) -> -0.078617992 | H9: =IFERROR((TimeLine!H9/TimeLine!H8)-1, NA()) -> -0.009059006 | I9: =IFERROR((TimeLine!I9/TimeLine!I8)-1, NA()) -> -0.057989691 | ... K9: =IFERROR((TimeLine!K9/TimeLine!K8)-1, NA()) -> -0.074325674
A10: =TimeLine!A10 -> 42248 | B10: =IFERROR((TimeLine!B10/TimeLine!B9)-1, NA()) -> -0.018011395 | C10: =IFERROR((TimeLine!C10/TimeLine!C9)-1, NA()) -> -0.011828814 | D10: =IFERROR((TimeLine!D10/TimeLine!D9)-1, NA()) -> -0.030555977 | E10: =IFERROR((TimeLine!E10/TimeLine!E9)-1, NA()) -> -0.048829953 | F10: =IFERROR((TimeLine!F10/TimeLine!F9)-1, NA()) -> 0.10714286 | G10: =IFERROR((TimeLine!G10/TimeLine!G9)-1, NA()) -> 0.01797085 | H10: =IFERROR((TimeLine!H10/TimeLine!H9)-1, NA()) -> 0.017460056 | I10: =IFERROR((TimeLine!I10/TimeLine!I9)-1, NA()) -> -0.02286496 | ... K10: =IFERROR((TimeLine!K10/TimeLine!K9)-1, NA()) -> -0.043384416
A11: =TimeLine!A11 -> 42278 | B11: =IFERROR((TimeLine!B11/TimeLine!B10)-1, NA()) -> 0.022833614 | C11: =IFERROR((TimeLine!C11/TimeLine!C10)-1, NA()) -> 0.11284465 | D11: =IFERROR((TimeLine!D11/TimeLine!D10)-1, NA()) -> 0.085059751 | E11: =IFERROR((TimeLine!E11/TimeLine!E10)-1, NA()) -> 0.053796949 | F11: =IFERROR((TimeLine!F11/TimeLine!F10)-1, NA()) -> 0.14516129 | G11: =IFERROR((TimeLine!G11/TimeLine!G10)-1, NA()) -> 0.061718098 | H11: =IFERROR((TimeLine!H11/TimeLine!H10)-1, NA()) -> -0.0061518537 | I11: =IFERROR((TimeLine!I11/TimeLine!I10)-1, NA()) -> 0.1046 | ... K11: =IFERROR((TimeLine!K11/TimeLine!K10)-1, NA()) -> 0.0625
A12: =TimeLine!A12 -> 42309 | B12: =IFERROR((TimeLine!B12/TimeLine!B11)-1, NA()) -> -0.067520586 | C12: =IFERROR((TimeLine!C12/TimeLine!C11)-1, NA()) -> -0.013052937 | D12: =IFERROR((TimeLine!D12/TimeLine!D11)-1, NA()) -> 0.0036550762 | E12: =IFERROR((TimeLine!E12/TimeLine!E11)-1, NA()) -> 0.037821012 | F12: =IFERROR((TimeLine!F12/TimeLine!F11)-1, NA()) -> 0.11267606 | G12: =IFERROR((TimeLine!G12/TimeLine!G11)-1, NA()) -> -0.020162346 | H12: =IFERROR((TimeLine!H12/TimeLine!H11)-1, NA()) -> -0.010832383 | I12: =IFERROR((TimeLine!I12/TimeLine!I11)-1, NA()) -> 0.011859497 | ... K12: =IFERROR((TimeLine!K12/TimeLine!K11)-1, NA()) -> -0.013166277
A13: =TimeLine!A13 -> 42339 | B13: =IFERROR((TimeLine!B13/TimeLine!B12)-1, NA()) -> -0.0045133438 | C13: =IFERROR((TimeLine!C13/TimeLine!C12)-1, NA()) -> -0.04543228 | D13: =IFERROR((TimeLine!D13/TimeLine!D12)-1, NA()) -> -0.023096459 | E13: =IFERROR((TimeLine!E13/TimeLine!E12)-1, NA()) -> -0.0097480504 | F13: =IFERROR((TimeLine!F13/TimeLine!F12)-1, NA()) -> 0.037974684 | G13: =IFERROR((TimeLine!G13/TimeLine!G12)-1, NA()) -> 0.061063602 | H13: =IFERROR((TimeLine!H13/TimeLine!H12)-1, NA()) -> -0.0071634417 | I13: =IFERROR((TimeLine!I13/TimeLine!I12)-1, NA()) -> -0.031135367 | ... K13: =IFERROR((TimeLine!K13/TimeLine!K12)-1, NA()) -> -0.029266193
A14: =TimeLine!A14 -> 42370 | B14: =IFERROR((TimeLine!B14/TimeLine!B13)-1, NA()) -> 0.054109994 | C14: =IFERROR((TimeLine!C14/TimeLine!C13)-1, NA()) -> -0.0012828736 | D14: =IFERROR((TimeLine!D14/TimeLine!D13)-1, NA()) -> -0.049786629 | E14: =IFERROR((TimeLine!E14/TimeLine!E13)-1, NA()) -> -0.098894442 | F14: =IFERROR((TimeLine!F14/TimeLine!F13)-1, NA()) -> -0.1097561 | G14: =IFERROR((TimeLine!G14/TimeLine!G13)-1, NA()) -> 0.028711749 | H14: =IFERROR((TimeLine!H14/TimeLine!H13)-1, NA()) -> 0.055730635 | I14: =IFERROR((TimeLine!I14/TimeLine!I13)-1, NA()) -> -0.058731185 | ... K14: =IFERROR((TimeLine!K14/TimeLine!K13)-1, NA()) -> -0.054533363
... A134: =TimeLine!A134 -> 46023 | B134: =IFERROR((TimeLine!B134/TimeLine!B133)-1, NA()) -> 0.063031465 | C134: =IFERROR((TimeLine!C134/TimeLine!C133)-1, NA()) -> 0.079358484 | D134: =IFERROR((TimeLine!D134/TimeLine!D133)-1, NA()) -> 0.0142832 | E134: =IFERROR((TimeLine!E134/TimeLine!E133)-1, NA()) -> -0.030258829 | F134: =IFERROR((TimeLine!F134/TimeLine!F133)-1, NA()) -> -0.0014477212 | G134: =IFERROR((TimeLine!G134/TimeLine!G133)-1, NA()) -> 0.0477287 | H134: =IFERROR((TimeLine!H134/TimeLine!H133)-1, NA()) -> 0.0053923818 | I134: =IFERROR((TimeLine!I134/TimeLine!I133)-1, NA()) -> -0.00027859588 | ... K134: =IFERROR((TimeLine!K134/TimeLine!K133)-1, NA()) -> 0.05421527

Sheet Returns2
A1: Date | B1: GLD | C1: XOM | D1: SPY | E1: JPM | F1: NVDA | G1: PG | H1: TLT | I1: VGT | J1: VNQ | K1: VXUS
A2: =TimeLine!A3 -> 42036 | B2: =IFERROR((TimeLine!B3/TimeLine!B2)-1, NA()) -> -0.059052248 | C2: =IFERROR((TimeLine!C3/TimeLine!C2)-1, NA()) -> 0.012811714 | D2: =IFERROR((TimeLine!D3/TimeLine!D2)-1, NA()) -> 0.056204563 | E2: =IFERROR((TimeLine!E3/TimeLine!E2)-1, NA()) -> 0.12688488 | F2: =IFERROR((TimeLine!F3/TimeLine!F2)-1, NA()) -> 0.14583333 | G2: =IFERROR((TimeLine!G3/TimeLine!G2)-1, NA()) -> 0.009965595 | H2: =IFERROR((TimeLine!H3/TimeLine!H2)-1, NA()) -> -0.063277408 | I2: =IFERROR((TimeLine!I3/TimeLine!I2)-1, NA()) -> 0.083325067 | ... K2: =IFERROR((TimeLine!K3/TimeLine!K2)-1, NA()) -> 0.057767691
A3: =TimeLine!A4 -> 42064 | B3: =IFERROR((TimeLine!B4/TimeLine!B3)-1, NA()) -> -0.021522039 | C3: =IFERROR((TimeLine!C4/TimeLine!C3)-1, NA()) -> -0.039981929 | D3: =IFERROR((TimeLine!D4/TimeLine!D3)-1, NA()) -> -0.020079749 | E3: =IFERROR((TimeLine!E4/TimeLine!E3)-1, NA()) -> -0.011422977 | F3: =IFERROR((TimeLine!F4/TimeLine!F3)-1, NA()) -> -0.054545455 | G3: =IFERROR((TimeLine!G4/TimeLine!G3)-1, NA()) -> -0.037472101 | H3: =IFERROR((TimeLine!H4/TimeLine!H3)-1, NA()) -> 0.0089554543 | I3: =IFERROR((TimeLine!I4/TimeLine!I3)-1, NA()) -> -0.024631444 | ... K3: =IFERROR((TimeLine!K4/TimeLine!K3)-1, NA()) -> -0.017944217
A4: =TimeLine!A5 -> 42095 | B4: =IFERROR((TimeLine!B5/TimeLine!B4)-1, NA()) -> -0.0016716523 | C4: =IFERROR((TimeLine!C5/TimeLine!C4)-1, NA()) -> 0.027882353 | D4: =IFERROR((TimeLine!D5/TimeLine!D4)-1, NA()) -> 0.009833842 | E4: =IFERROR((TimeLine!E5/TimeLine!E4)-1, NA()) -> 0.044239023 | F4: =IFERROR((TimeLine!F5/TimeLine!F4)-1, NA()) -> 0.057692308 | G4: =IFERROR((TimeLine!G5/TimeLine!G4)-1, NA()) -> -0.029655846 | H4: =IFERROR((TimeLine!H5/TimeLine!H4)-1, NA()) -> -0.036269034 | I4: =IFERROR((TimeLine!I5/TimeLine!I4)-1, NA()) -> 0.012861434 | ... K4: =IFERROR((TimeLine!K5/TimeLine!K4)-1, NA()) -> 0.048063555
A5: =TimeLine!A6 -> 42125 | B5: =IFERROR((TimeLine!B6/TimeLine!B5)-1, NA()) -> 0.0055521283 | C5: =IFERROR((TimeLine!C6/TimeLine!C5)-1, NA()) -> -0.024836901 | D5: =IFERROR((TimeLine!D6/TimeLine!D5)-1, NA()) -> 0.012856183 | E5: =IFERROR((TimeLine!E6/TimeLine!E5)-1, NA()) -> 0.039835599 | F5: =IFERROR((TimeLine!F6/TimeLine!F5)-1, NA()) -> 0 | G5: =IFERROR((TimeLine!G6/TimeLine!G5)-1, NA()) -> -0.014086278 | H5: =IFERROR((TimeLine!H6/TimeLine!H5)-1, NA()) -> -0.025724494 | I5: =IFERROR((TimeLine!I6/TimeLine!I5)-1, NA()) -> 0.024932802 | ... K5: =IFERROR((TimeLine!K6/TimeLine!K5)-1, NA()) -> -0.0090960773
A6: =TimeLine!A7 -> 42156 | B6: =IFERROR((TimeLine!B7/TimeLine!B6)-1, NA()) -> -0.015162138 | C6: =IFERROR((TimeLine!C7/TimeLine!C6)-1, NA()) -> -0.023474178 | D6: =IFERROR((TimeLine!D7/TimeLine!D6)-1, NA()) -> -0.025054466 | E6: =IFERROR((TimeLine!E7/TimeLine!E6)-1, NA()) -> 0.030100334 | F6: =IFERROR((TimeLine!F7/TimeLine!F6)-1, NA()) -> -0.090909091 | G6: =IFERROR((TimeLine!G7/TimeLine!G6)-1, NA()) -> -0.0019135094 | H6: =IFERROR((TimeLine!H7/TimeLine!H6)-1, NA()) -> -0.042783799 | I6: =IFERROR((TimeLine!I7/TimeLine!I6)-1, NA()) -> -0.039338036 | ... K6: =IFERROR((TimeLine!K7/TimeLine!K6)-1, NA()) -> -0.037483266
A7: =TimeLine!A8 -> 42186 | B7: =IFERROR((TimeLine!B8/TimeLine!B7)-1, NA()) -> -0.066209842 | C7: =IFERROR((TimeLine!C8/TimeLine!C7)-1, NA()) -> -0.047956731 | D7: =IFERROR((TimeLine!D8/TimeLine!D7)-1, NA()) -> 0.022589264 | E7: =IFERROR((TimeLine!E8/TimeLine!E7)-1, NA()) -> 0.011363636 | F7: =IFERROR((TimeLine!F8/TimeLine!F7)-1, NA()) -> 0 | G7: =IFERROR((TimeLine!G8/TimeLine!G7)-1, NA()) -> -0.019683027 | H7: =IFERROR((TimeLine!H8/TimeLine!H7)-1, NA()) -> 0.04316363 | I7: =IFERROR((TimeLine!I8/TimeLine!I7)-1, NA()) -> 0.022686623 | ... K7: =IFERROR((TimeLine!K8/TimeLine!K7)-1, NA()) -> -0.0055632823
A8: =TimeLine!A9 -> 42217 | B8: =IFERROR((TimeLine!B9/TimeLine!B8)-1, NA()) -> 0.037072334 | C8: =IFERROR((TimeLine!C9/TimeLine!C8)-1, NA()) -> -0.050119934 | D8: =IFERROR((TimeLine!D9/TimeLine!D8)-1, NA()) -> -0.060950119 | E8: =IFERROR((TimeLine!E9/TimeLine!E8)-1, NA()) -> -0.064643222 | F8: =IFERROR((TimeLine!F9/TimeLine!F8)-1, NA()) -> 0.12 | G8: =IFERROR((TimeLine!G9/TimeLine!G8)-1, NA()) -> -0.078617992 | H8: =IFERROR((TimeLine!H9/TimeLine!H8)-1, NA()) -> -0.009059006 | I8: =IFERROR((TimeLine!I9/TimeLine!I8)-1, NA()) -> -0.057989691 | ... K8: =IFERROR((TimeLine!K9/TimeLine!K8)-1, NA()) -> -0.074325674
A9: =TimeLine!A10 -> 42248 | B9: =IFERROR((TimeLine!B10/TimeLine!B9)-1, NA()) -> -0.018011395 | C9: =IFERROR((TimeLine!C10/TimeLine!C9)-1, NA()) -> -0.011828814 | D9: =IFERROR((TimeLine!D10/TimeLine!D9)-1, NA()) -> -0.030555977 | E9: =IFERROR((TimeLine!E10/TimeLine!E9)-1, NA()) -> -0.048829953 | F9: =IFERROR((TimeLine!F10/TimeLine!F9)-1, NA()) -> 0.10714286 | G9: =IFERROR((TimeLine!G10/TimeLine!G9)-1, NA()) -> 0.01797085 | H9: =IFERROR((TimeLine!H10/TimeLine!H9)-1, NA()) -> 0.017460056 | I9: =IFERROR((TimeLine!I10/TimeLine!I9)-1, NA()) -> -0.02286496 | ... K9: =IFERROR((TimeLine!K10/TimeLine!K9)-1, NA()) -> -0.043384416
A10: =TimeLine!A11 -> 42278 | B10: =IFERROR((TimeLine!B11/TimeLine!B10)-1, NA()) -> 0.022833614 | C10: =IFERROR((TimeLine!C11/TimeLine!C10)-1, NA()) -> 0.11284465 | D10: =IFERROR((TimeLine!D11/TimeLine!D10)-1, NA()) -> 0.085059751 | E10: =IFERROR((TimeLine!E11/TimeLine!E10)-1, NA()) -> 0.053796949 | F10: =IFERROR((TimeLine!F11/TimeLine!F10)-1, NA()) -> 0.14516129 | G10: =IFERROR((TimeLine!G11/TimeLine!G10)-1, NA()) -> 0.061718098 | H10: =IFERROR((TimeLine!H11/TimeLine!H10)-1, NA()) -> -0.0061518537 | I10: =IFERROR((TimeLine!I11/TimeLine!I10)-1, NA()) -> 0.1046 | ... K10: =IFERROR((TimeLine!K11/TimeLine!K10)-1, NA()) -> 0.0625
A11: =TimeLine!A12 -> 42309 | B11: =IFERROR((TimeLine!B12/TimeLine!B11)-1, NA()) -> -0.067520586 | C11: =IFERROR((TimeLine!C12/TimeLine!C11)-1, NA()) -> -0.013052937 | D11: =IFERROR((TimeLine!D12/TimeLine!D11)-1, NA()) -> 0.0036550762 | E11: =IFERROR((TimeLine!E12/TimeLine!E11)-1, NA()) -> 0.037821012 | F11: =IFERROR((TimeLine!F12/TimeLine!F11)-1, NA()) -> 0.11267606 | G11: =IFERROR((TimeLine!G12/TimeLine!G11)-1, NA()) -> -0.020162346 | H11: =IFERROR((TimeLine!H12/TimeLine!H11)-1, NA()) -> -0.010832383 | I11: =IFERROR((TimeLine!I12/TimeLine!I11)-1, NA()) -> 0.011859497 | ... K11: =IFERROR((TimeLine!K12/TimeLine!K11)-1, NA()) -> -0.013166277
A12: =TimeLine!A13 -> 42339 | B12: =IFERROR((TimeLine!B13/TimeLine!B12)-1, NA()) -> -0.0045133438 | C12: =IFERROR((TimeLine!C13/TimeLine!C12)-1, NA()) -> -0.04543228 | D12: =IFERROR((TimeLine!D13/TimeLine!D12)-1, NA()) -> -0.023096459 | E12: =IFERROR((TimeLine!E13/TimeLine!E12)-1, NA()) -> -0.0097480504 | F12: =IFERROR((TimeLine!F13/TimeLine!F12)-1, NA()) -> 0.037974684 | G12: =IFERROR((TimeLine!G13/TimeLine!G12)-1, NA()) -> 0.061063602 | H12: =IFERROR((TimeLine!H13/TimeLine!H12)-1, NA()) -> -0.0071634417 | I12: =IFERROR((TimeLine!I13/TimeLine!I12)-1, NA()) -> -0.031135367 | ... K12: =IFERROR((TimeLine!K13/TimeLine!K12)-1, NA()) -> -0.029266193
A13: =TimeLine!A14 -> 42370 | B13: =IFERROR((TimeLine!B14/TimeLine!B13)-1, NA()) -> 0.054109994 | C13: =IFERROR((TimeLine!C14/TimeLine!C13)-1, NA()) -> -0.0012828736 | D13: =IFERROR((TimeLine!D14/TimeLine!D13)-1, NA()) -> -0.049786629 | E13: =IFERROR((TimeLine!E14/TimeLine!E13)-1, NA()) -> -0.098894442 | F13: =IFERROR((TimeLine!F14/TimeLine!F13)-1, NA()) -> -0.1097561 | G13: =IFERROR((TimeLine!G14/TimeLine!G13)-1, NA()) -> 0.028711749 | H13: =IFERROR((TimeLine!H14/TimeLine!H13)-1, NA()) -> 0.055730635 | I13: =IFERROR((TimeLine!I14/TimeLine!I13)-1, NA()) -> -0.058731185 | ... K13: =IFERROR((TimeLine!K14/TimeLine!K13)-1, NA()) -> -0.054533363
... A133: =TimeLine!A134 -> 46023 | B133: =IFERROR((TimeLine!B134/TimeLine!B133)-1, NA()) -> 0.063031465 | C133: =IFERROR((TimeLine!C134/TimeLine!C133)-1, NA()) -> 0.079358484 | D133: =IFERROR((TimeLine!D134/TimeLine!D133)-1, NA()) -> 0.0142832 | E133: =IFERROR((TimeLine!E134/TimeLine!E133)-1, NA()) -> -0.030258829 | F133: =IFERROR((TimeLine!F134/TimeLine!F133)-1, NA()) -> -0.0014477212 | G133: =IFERROR((TimeLine!G134/TimeLine!G133)-1, NA()) -> 0.0477287 | H133: =IFERROR((TimeLine!H134/TimeLine!H133)-1, NA()) -> 0.0053923818 | I133: =IFERROR((TimeLine!I134/TimeLine!I133)-1, NA()) -> -0.00027859588 | ... K133: =IFERROR((TimeLine!K134/TimeLine!K133)-1, NA()) -> 0.05421527

Sheet Risk_Analysis
A1: Risk & Return
A2: Metric | B2: GLD | C2: XOM | D2: SPY | E2: JPM | F2: NVDA | G2: PG | H2: TLT | I2: VGT | J2: VNQ | K2: VXUS
A3: Mean (Monthly) | B3: =AVERAGE(Returns!B3:B134) -> 0.010176236 | C3: =AVERAGE(Returns!C3:C134) -> 0.0058544244 | D3: =AVERAGE(Returns!D3:D134) -> 0.010405797 | E3: =AVERAGE(Returns!E3:E134) -> 0.015624227 | F3: =AVERAGE(Returns!F3:F134) -> 0.054681936 | G3: =AVERAGE(Returns!G3:G134) -> 0.0054087935 | H3: =AVERAGE(Returns!H3:H134) -> -0.0027144972 | I3: =AVERAGE(Returns!I3:I134) -> 0.016933095 | ... K3: =AVERAGE(Returns!K3:K134) -> 0.0046811889
A4: Std Dev (Monthly) | B4: =_xlfn.STDEV.S(Returns!B3:B134) -> 0.041340507 | C4: =_xlfn.STDEV.S(Returns!C3:C134) -> 0.076034359 | D4: =_xlfn.STDEV.S(Returns!D3:D134) -> 0.043432228 | E4: =_xlfn.STDEV.S(Returns!E3:E134) -> 0.067971877 | F4: =_xlfn.STDEV.S(Returns!F3:F134) -> 0.13247904 | G4: =_xlfn.STDEV.S(Returns!G3:G134) -> 0.045545855 | H4: =_xlfn.STDEV.S(Returns!H3:H134) -> 0.038526618 | I4: =_xlfn.STDEV.S(Returns!I3:I134) -> 0.056523773 | ... K4: =_xlfn.STDEV.S(Returns!K3:K134) -> 0.04292215
A5: Mean (Annualized) | B5: =B3*12 -> 0.12211484 | C5: =C3*12 -> 0.070253093 | D5: =D3*12 -> 0.12486957 | E5: =E3*12 -> 0.18749072 | F5: =F3*12 -> 0.65618323 | G5: =G3*12 -> 0.064905522 | H5: =H3*12 -> -0.032573967 | I5: =I3*12 -> 0.20319714 | ... K5: =K3*12 -> 0.056174267
A6: Std Dev (Annualized) | B6: =B4*SQRT(12) -> 0.14320772 | C6: =C4*SQRT(12) -> 0.26339074 | D6: =D4*SQRT(12) -> 0.15045365 | E6: =E4*SQRT(12) -> 0.23546149 | F6: =F4*SQRT(12) -> 0.45892084 | G6: =G4*SQRT(12) -> 0.15777547 | H6: =H4*SQRT(12) -> 0.13346012 | I6: =I4*SQRT(12) -> 0.19580409 | ... K6: =K4*SQRT(12) -> 0.14868669
A7: Sharpe Ratio | B7: =(B5-Risk_Free_rate)/B6 -> 0.57339672 | C7: =(C5-Risk_Free_rate)/C6 -> 0.11486012 | D7: =(D5-Risk_Free_rate)/D6 -> 0.56409112 | E7: =(E5-Risk_Free_rate)/E6 -> 0.62639001 | F7: =(F5-Risk_Free_rate)/F6 -> 1.3426787 | G7: =(G5-Risk_Free_rate)/G6 -> 0.15785421 | H7: =(H5-Risk_Free_rate)/H6 -> -0.54378766 | I7: =(I5-Risk_Free_rate)/I6 -> 0.83347153 | ... K7: =(K5-Risk_Free_rate)/K6 -> 0.10878087
A13: Risk-Free Rate | B13: 0.04

Sheet Correlation
A1: correlation matrix
B2: GLD | C2: XOM | D2: SPY | E2: JPM | F2: NVDA | G2: PG | H2: TLT | I2: VGT | J2: VNQ | K2: VXUS
A3: GLD | B3: 1
A4: XOM | B4: -0.052602678 | C4: 1
A5: SPY | B5: 0.075629895 | C5: 0.48664066 | D5: 1
A6: JPM | B6: -0.15478792 | C6: 0.48366787 | D6: 0.72201194 | E6: 1
A7: NVDA | B7: -0.07135285 | C7: 0.11593509 | D7: 0.58524839 | E7: 0.33253514 | F7: 1
A8: PG | B8: 0.21463343 | C8: 0.15856126 | D8: 0.36666489 | E8: 0.13910832 | F8: 0.0057880811 | G8: 1
A9: TLT | B9: 0.37669484 | C9: -0.21709239 | D9: 0.13737213 | E9: -0.17214217 | F9: 0.14482298 | G9: 0.16097344 | H9: 1
A10: VGT | B10: 0.019545019 | C10: 0.28565349 | D10: 0.90790238 | E10: 0.54603734 | F10: 0.71804122 | G10: 0.24635804 | H10: 0.19899337 | I10: 1
A11: VNQ | B11: 0.16130328 | C11: 0.38133903 | D11: 0.76601496 | E11: 0.47083064 | F11: 0.29478893 | G11: 0.43599369 | H11: 0.4180469 | I11: 0.61115323 | J11: 1
A12: VXUS | B12: 0.23445849 | C12: 0.48602043 | D12: 0.84742524 | E12: 0.67252338 | F12: 0.44102698 | G12: 0.3195242 | H12: 0.15733104 | I12: 0.72499146 | J12: 0.69270347 | K12: 1

Sheet Beta
B1: GLD | C1: XOM | D1: SPY | E1: JPM | F1: NVDA | G1: PG | H1: TLT | I1: VGT | J1: VNQ | K1: VXUS
A2: Beta | B2: =_xlfn.COVARIANCE.S(Returns!B3:B1000, Returns!$D$3:$D$1000) / _xlfn.VAR.S(Returns!$D$3:$D$1000) -> 0.071987516 | C2: =_xlfn.COVARIANCE.S(Returns!C3:C1000, Returns!$D$3:$D$1000) / _xlfn.VAR.S(Returns!$D$3:$D$1000) -> 0.85193442 | D2: =_xlfn.COVARIANCE.S(Returns!D3:D1000, Returns!$D$3:$D$1000) / _xlfn.VAR.S(Returns!$D$3:$D$1000) -> 1 | E2: =_xlfn.COVARIANCE.S(Returns!E3:E1000, Returns!$D$3:$D$1000) / _xlfn.VAR.S(Returns!$D$3:$D$1000) -> 1.129956 | F2: =_xlfn.COVARIANCE.S(Returns!F3:F1000, Returns!$D$3:$D$1000) / _xlfn.VAR.S(Returns!$D$3:$D$1000) -> 1.7851523 | G2: =_xlfn.COVARIANCE.S(Returns!G3:G1000, Returns!$D$3:$D$1000) / _xlfn.VAR.S(Returns!$D$3:$D$1000) -> 0.38450862 | H2: =_xlfn.COVARIANCE.S(Returns!H3:H1000, Returns!$D$3:$D$1000) / _xlfn.VAR.S(Returns!$D$3:$D$1000) -> 0.12185614 | I2: =_xlfn.COVARIANCE.S(Returns!I3:I1000, Returns!$D$3:$D$1000) / _xlfn.VAR.S(Returns!$D$3:$D$1000) -> 1.1815666 | ... K2: =_xlfn.COVARIANCE.S(Returns!K3:K1000, Returns!$D$3:$D$1000) / _xlfn.VAR.S(Returns!$D$3:$D$1000) -> 0.83747288

Sheet Portfolio 
A1: Portfolio Composition
A2: Asset | B2: Weight | C2: Mean (Annualized)
A3: GLD | B3: 0.1 | C3: =INDEX(Risk_Analysis!$B$5:$K$5, MATCH(A3, Risk_Analysis!$B$2:$K$2, 0)) -> 0.12211484
A4: XOM | B4: 0.05 | C4: =INDEX(Risk_Analysis!$B$5:$K$5, MATCH(A4, Risk_Analysis!$B$2:$K$2, 0)) -> 0.070253093
A5: SPY | B5: 0.25 | C5: =INDEX(Risk_Analysis!$B$5:$K$5, MATCH(A5, Risk_Analysis!$B$2:$K$2, 0)) -> 0.12486957
A6: JPM | B6: 0.05 | C6: =INDEX(Risk_Analysis!$B$5:$K$5, MATCH(A6, Risk_Analysis!$B$2:$K$2, 0)) -> 0.18749072
A7: NVDA | B7: 0.05 | C7: =INDEX(Risk_Analysis!$B$5:$K$5, MATCH(A7, Risk_Analysis!$B$2:$K$2, 0)) -> 0.65618323
A8: PG | B8: 0.05 | C8: =INDEX(Risk_Analysis!$B$5:$K$5, MATCH(A8, Risk_Analysis!$B$2:$K$2, 0)) -> 0.064905522
A9: TLT | B9: 0.1 | C9: =INDEX(Risk_Analysis!$B$5:$K$5, MATCH(A9, Risk_Analysis!$B$2:$K$2, 0)) -> -0.032573967
A10: VGT | B10: 0.1 | C10: =INDEX(Risk_Analysis!$B$5:$K$5, MATCH(A10, Risk_Analysis!$B$2:$K$2, 0)) -> 0.20319714
A11: VNQ | B11: 0.1 | C11: =INDEX(Risk_Analysis!$B$5:$K$5, MATCH(A11, Risk_Analysis!$B$2:$K$2, 0)) -> 0.019361355
A12: VXUS | B12: 0.15 | C12: =INDEX(Risk_Analysis!$B$5:$K$5, MATCH(A12, Risk_Analysis!$B$2:$K$2, 0)) -> 0.056174267
A16: Expected Annual Return | B16: =SUMPRODUCT(B3:B12, C3:C12) -> 0.1197951
A20: covariance matrix
B21: GLD | C21: XOM | D21: SPY | E21: JPM | F21: NVDA | G21: PG | H21: TLT | I21: VGT | J21: VNQ | K21: VXUS
A22: GLD | B22: =VARP(Returns!$B$3:$B$134) -> 0.0016960903 | C22: =INDEX($B$22:$K$31, MATCH(C$21, $A$22:$A$31, 0), MATCH($A22, $B$21:$K$21, 0)) -> -0.00016409332 | D22: =INDEX($B$22:$K$31, MATCH(D$21, $A$22:$A$31, 0), MATCH($A22, $B$21:$K$21, 0)) -> 0.00013476552 | E22: =INDEX($B$22:$K$31, MATCH(E$21, $A$22:$A$31, 0), MATCH($A22, $B$21:$K$21, 0)) -> -0.00043165769 | F22: =INDEX($B$22:$K$31, MATCH(F$21, $A$22:$A$31, 0), MATCH($A22, $B$21:$K$21, 0)) -> -0.00038782129 | G22: =INDEX($B$22:$K$31, MATCH(G$21, $A$22:$A$31, 0), MATCH($A22, $B$21:$K$21, 0)) -> 0.00040106929 | H22: =INDEX($B$22:$K$31, MATCH(H$21, $A$22:$A$31, 0), MATCH($A22, $B$21:$K$21, 0)) -> 0.00059542042 | I22: =INDEX($B$22:$K$31, MATCH(I$21, $A$22:$A$31, 0), MATCH($A22, $B$21:$K$21, 0)) -> 4.532527e-05 | J22: =INDEX($B$22:$K$31, MATCH(J$21, $A$22:$A$31, 0), MATCH($A22, $B$21:$K$21, 0)) -> 0.00033398049 | K22: =INDEX($B$22:$K$31, MATCH(K$21, $A$22:$A$31, 0), MATCH($A22, $B$21:$K$21, 0)) -> 0.00041287691
A23: XOM | B23: -0.00016409332 | C23: =VARP(Returns!$C$3:$C$134) -> 0.0057374265 | D23: =INDEX($B$22:$K$31, MATCH(D$21, $A$22:$A$31, 0), MATCH($A23, $B$21:$K$21, 0)) -> 0.001594879 | E23: =INDEX($B$22:$K$31, MATCH(E$21, $A$22:$A$31, 0), MATCH($A23, $B$21:$K$21, 0)) -> 0.0024807543 | F23: =INDEX($B$22:$K$31, MATCH(F$21, $A$22:$A$31, 0), MATCH($A23, $B$21:$K$21, 0)) -> 0.0011589623 | G23: =INDEX($B$22:$K$31, MATCH(G$21, $A$22:$A$31, 0), MATCH($A23, $B$21:$K$21, 0)) -> 0.00054494567 | H23: =INDEX($B$22:$K$31, MATCH(H$21, $A$22:$A$31, 0), MATCH($A23, $B$21:$K$21, 0)) -> -0.00063112117 | I23: =INDEX($B$22:$K$31, MATCH(I$21, $A$22:$A$31, 0), MATCH($A23, $B$21:$K$21, 0)) -> 0.0012183664 | J23: =INDEX($B$22:$K$31, MATCH(J$21, $A$22:$A$31, 0), MATCH($A23, $B$21:$K$21, 0)) -> 0.0014521893 | K23: =INDEX($B$22:$K$31, MATCH(K$21, $A$22:$A$31, 0), MATCH($A23, $B$21:$K$21, 0)) -> 0.0015741396
A24: SPY | B24: 0.00013476552 | C24: 0.001594879 | D24: =VARP(Returns!$D$3:$D$134) -> 0.0018720679 | E24: =INDEX($B$22:$K$31, MATCH(E$21, $A$22:$A$31, 0), MATCH($A24, $B$21:$K$21, 0)) -> 0.0021153543 | F24: =INDEX($B$22:$K$31, MATCH(F$21, $A$22:$A$31, 0), MATCH($A24, $B$21:$K$21, 0)) -> 0.0033419262 | G24: =INDEX($B$22:$K$31, MATCH(G$21, $A$22:$A$31, 0), MATCH($A24, $B$21:$K$21, 0)) -> 0.00071982622 | H24: =INDEX($B$22:$K$31, MATCH(H$21, $A$22:$A$31, 0), MATCH($A24, $B$21:$K$21, 0)) -> 0.00022812296 | I24: =INDEX($B$22:$K$31, MATCH(I$21, $A$22:$A$31, 0), MATCH($A24, $B$21:$K$21, 0)) -> 0.0022119728 | J24: =INDEX($B$22:$K$31, MATCH(J$21, $A$22:$A$31, 0), MATCH($A24, $B$21:$K$21, 0)) -> 0.0016662933 | K24: =INDEX($B$22:$K$31, MATCH(K$21, $A$22:$A$31, 0), MATCH($A24, $B$21:$K$21, 0)) -> 0.0015678061
A25: JPM | B25: -0.00043165769 | C25: 0.0024807543 | D25: 0.0021153543 | E25: =VARP(Returns!$E$3:$E$134) -> 0.0045851747 | F25: =INDEX($B$22:$K$31, MATCH(F$21, $A$22:$A$31, 0), MATCH($A25, $B$21:$K$21, 0)) -> 0.0029717435 | G25: =INDEX($B$22:$K$31, MATCH(G$21, $A$22:$A$31, 0), MATCH($A25, $B$21:$K$21, 0)) -> 0.00042739417 | H25: =INDEX($B$22:$K$31, MATCH(H$21, $A$22:$A$31, 0), MATCH($A25, $B$21:$K$21, 0)) -> -0.00044737816 | I25: =INDEX($B$22:$K$31, MATCH(I$21, $A$22:$A$31, 0), MATCH($A25, $B$21:$K$21, 0)) -> 0.0020819971 | J25: =INDEX($B$22:$K$31, MATCH(J$21, $A$22:$A$31, 0), MATCH($A25, $B$21:$K$21, 0)) -> 0.0016028618 | K25: =INDEX($B$22:$K$31, MATCH(K$21, $A$22:$A$31, 0), MATCH($A25, $B$21:$K$21, 0)) -> 0.001947222
A26: NVDA | B26: -0.00038782129 | C26: 0.0011589623 | D26: 0.0033419262 | E26: 0.0029717435 | F26: =VARP(Returns!$F$3:$F$134) -> 0.017417735 | G26: =INDEX($B$22:$K$31, MATCH(G$21, $A$22:$A$31, 0), MATCH($A26, $B$21:$K$21, 0)) -> 3.4659955e-05 | H26: =INDEX($B$22:$K$31, MATCH(H$21, $A$22:$A$31, 0), MATCH($A26, $B$21:$K$21, 0)) -> 0.00073357227 | I26: =INDEX($B$22:$K$31, MATCH(I$21, $A$22:$A$31, 0), MATCH($A26, $B$21:$K$21, 0)) -> 0.0053361133 | J26: =INDEX($B$22:$K$31, MATCH(J$21, $A$22:$A$31, 0), MATCH($A26, $B$21:$K$21, 0)) -> 0.001955962 | K26: =INDEX($B$22:$K$31, MATCH(K$21, $A$22:$A$31, 0), MATCH($A26, $B$21:$K$21, 0)) -> 0.0024888066
A27: PG | B27: 0.00040106929 | C27: 0.00054494567 | D27: 0.00071982622 | E27: 0.00042739417 | F27: 3.4659955e-05 | G27: =VARP(Returns!$G$3:$G$134) -> 0.0020587096 | H27: =INDEX($B$22:$K$31, MATCH(H$21, $A$22:$A$31, 0), MATCH($A27, $B$21:$K$21, 0)) -> 0.00028032469 | I27: =INDEX($B$22:$K$31, MATCH(I$21, $A$22:$A$31, 0), MATCH($A27, $B$21:$K$21, 0)) -> 0.00062942519 | J27: =INDEX($B$22:$K$31, MATCH(J$21, $A$22:$A$31, 0), MATCH($A27, $B$21:$K$21, 0)) -> 0.0009945604 | K27: =INDEX($B$22:$K$31, MATCH(K$21, $A$22:$A$31, 0), MATCH($A27, $B$21:$K$21, 0)) -> 0.00061991401
A28: TLT | B28: 0.00059542042 | C28: -0.00063112117 | D28: 0.00022812296 | E28: -0.00044737816 | F28: 0.00073357227 | G28: 0.00028032469 | H28: =VARP(Returns!$H$3:$H$134) -> 0.0014730556 | I28: =INDEX($B$22:$K$31, MATCH(I$21, $A$22:$A$31, 0), MATCH($A28, $B$21:$K$21, 0)) -> 0.00043005896 | J28: =INDEX($B$22:$K$31, MATCH(J$21, $A$22:$A$31, 0), MATCH($A28, $B$21:$K$21, 0)) -> 0.00080665529 | K28: =INDEX($B$22:$K$31, MATCH(K$21, $A$22:$A$31, 0), MATCH($A28, $B$21:$K$21, 0)) -> 0.00025819874
A29: VGT | B29: 4.532527e-05 | C29: 0.0012183664 | D29: 0.0022119728 | E29: 0.0020819971 | F29: 0.0053361133 | G29: 0.00062942519 | H29: 0.00043005896 | I29: =VARP(Returns!$I$3:$I$134) -> 0.0031707328 | J29: =INDEX($B$22:$K$31, MATCH(J$21, $A$22:$A$31, 0), MATCH($A29, $B$21:$K$21, 0)) -> 0.0017301484 | K29: =INDEX($B$22:$K$31, MATCH(K$21, $A$22:$A$31, 0), MATCH($A29, $B$21:$K$21, 0)) -> 0.0017455925
A30: VNQ | B30: 0.00033398049 | C30: 0.0014521893 | D30: 0.0016662933 | E30: 0.0016028618 | F30: 0.001955962 | G30: 0.0009945604 | H30: 0.00080665529 | I30: 0.0017301484 | J30: =VARP(Returns!$J$3:$J$134) -> 0.0025275911 | K30: =INDEX($B$22:$K$31, MATCH(K$21, $A$22:$A$31, 0), MATCH($A30, $B$21:$K$21, 0)) -> 0.0014891242
A31: VXUS | B31: 0.00041287691 | C31: 0.0015741396 | D31: 0.0015678061 | E31: 0.001947222 | F31: 0.0024888066 | G31: 0.00061991401 | H31: 0.00025819874 | I31: 0.0017455925 | J31: 0.0014891242 | K31: =VARP(Returns!$K$3:$K$134) -> 0.0018283541
A34: Weight Transpose | B34: {=TRANSPOSE(B3:B12)} -> 0.1 | C34: 0.05 | D34: 0.25 | E34: 0.05 | F34: 0.05 | G34: 0.05 | H34: 0.1 | I34: 0.1 | J34: 0.1 | K34: 0.15
A37: Monthly Variance | B37: =MMULT( MMULT($B$34:$K$34, $B$22:$K$31), $B$3:$B$12 ) -> 0.0013250501
A38: Monthly Volatility | B38: =SQRT(B37) -> 0.036401238
A39: Annualized Volatility | B39: =B38*SQRT(12) -> 0.12609759
A40: Sharpe Ratio | B40: =(B16-Risk_Free_rate)/B39 -> 0.63280431

Sheet Solver_Optimization
E1: Expected Annual Return | F1: Portfolio Sharp | G1: sum of | H1: Risk-Free Rate | I1: Portfolio Volatility (Annualized) | J1: Portfolio Variance (Monthly)
E2: =SUMPRODUCT(B6:B15, C6:C15) -> 0.21181043 | F2: =(E2-H2)/I2 -> 1.1705843 | G2: =SUM(B6:B15) -> 1 | H2: 0.04 | I2: =SQRT(J2)*SQRT(12) -> 0.14677322 | J2: {=MMULT(TRANSPOSE($B$6:$B$15),MMULT($N$3:$W$12,$B$6:$B$15))} -> 0.0017951983 | N2: GLD | O2: XOM | P2: SPY | Q2: JPM | R2: NVDA | S2: PG | T2: TLT | U2: VGT | V2: VNQ | W2: VXUS
M3: GLD | N3: 0.0016960903 | O3: -0.00016409332 | P3: 0.00013476552 | Q3: -0.00043165769 | R3: -0.00038782129 | S3: 0.00040106929 | T3: 0.00059542042 | U3: 4.532527e-05 | V3: 0.00033398049 | W3: 0.00041287691
M4: XOM | N4: -0.00016409332 | O4: 0.0057374265 | P4: 0.001594879 | Q4: 0.0024807543 | R4: 0.0011589623 | S4: 0.00054494567 | T4: -0.00063112117 | U4: 0.0012183664 | V4: 0.0014521893 | W4: 0.0015741396
A5: Asset | B5: Weight | C5: Mean (Annual) | D5: MIN | E5: MAX | M5: SPY | N5: 0.00013476552 | O5: 0.001594879 | P5: 0.0018720679 | Q5: 0.0021153543 | R5: 0.0033419262 | S5: 0.00071982622 | T5: 0.00022812296 | U5: 0.0022119728 | V5: 0.0016662933 | W5: 0.0015678061
A6: GLD | B6: 0.2 | C6: =Risk_Analysis!B5 -> 0.12211484 | D6: 0.05 | E6: 0.2 | M6: JPM | N6: -0.00043165769 | O6: 0.0024807543 | P6: 0.0021153543 | Q6: 0.0045851747 | R6: 0.0029717435 | S6: 0.00042739417 | T6: -0.00044737816 | U6: 0.0020819971 | V6: 0.0016028618 | W6: 0.001947222
A7: XOM | B7: 0 | C7: =Risk_Analysis!C5 -> 0.070253093 | D7: 0 | E7: 0.1 | M7: NVDA | N7: -0.00038782129 | O7: 0.0011589623 | P7: 0.0033419262 | Q7: 0.0029717435 | R7: 0.017417735 | S7: 3.4659955e-05 | T7: 0.00073357227 | U7: 0.0053361133 | V7: 0.001955962 | W7: 0.0024888066
A8: SPY | B8: 0.25 | C8: =Risk_Analysis!D5 -> 0.12486957 | D8: 0.25 | E8: 0.4 | M8: PG | N8: 0.00040106929 | O8: 0.00054494567 | P8: 0.00071982622 | Q8: 0.00042739417 | R8: 3.4659955e-05 | S8: 0.0020587096 | T8: 0.00028032469 | U8: 0.00062942519 | V8: 0.0009945604 | W8: 0.00061991401
A9: JPM | B9: 0.15 | C9: =Risk_Analysis!E5 -> 0.18749072 | D9: 0 | E9: 0.15 | M9: TLT | N9: 0.00059542042 | O9: -0.00063112117 | P9: 0.00022812296 | Q9: -0.00044737816 | R9: 0.00073357227 | S9: 0.00028032469 | T9: 0.0014730556 | U9: 0.00043005896 | V9: 0.00080665529 | W9: 0.00025819874
A10: NVDA | B10: 0.15 | C10: =Risk_Analysis!F$5 -> 0.65618323 | D10: 0 | E10: 0.15 | M10: VGT | N10: 4.532527e-05 | O10: 0.0012183664 | P10: 0.0022119728 | Q10: 0.0020819971 | R10: 0.0053361133 | S10: 0.00062942519 | T10: 0.00043005896 | U10: 0.0031707328 | V10: 0.0017301484 | W10: 0.0017455925
A11: PG | B11: 0.1 | C11: =Risk_Analysis!G5 -> 0.064905522 | D11: 0 | E11: 0.1 | M11: VNQ | N11: 0.00033398049 | O11: 0.0014521893 | P11: 0.0016662933 | Q11: 0.0016028618 | R11: 0.001955962 | S11: 0.0009945604 | T11: 0.00080665529 | U11: 0.0017301484 | V11: 0.0025275911 | W11: 0.0014891242
A12: TLT | B12: 0 | C12: =Risk_Analysis!H5 -> -0.032573967 | D12: 0 | E12: 0.2 | M12: VXUS | N12: 0.00041287691 | O12: 0.0015741396 | P12: 0.0015678061 | Q12: 0.001947222 | R12: 0.0024888066 | S12: 0.00061991401 | T12: 0.00025819874 | U12: 0.0017455925 | V12: 0.0014891242 | W12: 0.0018283541
A13: VGT | B13: 0.099999999 | C13: =Risk_Analysis!I5 -> 0.20319714 | D13: 0 | E13: 0.15
A14: VNQ | B14: 0 | C14: =Risk_Analysis!J5 -> 0.019361355 | D14: 0 | E14: 0.15
A15: VXUS | B15: 0.05 | C15: =Risk_Analysis!K5 -> 0.056174267 | D15: 0.05 | E15: 0.2
A26: μ (Train)
A27: Asset | B27: Mean | C27: Weights | D27: MIN | E27: MAX | G27: Variance (Train) | H27: Volatility (Train) | I27: Expected Return (Train) | J27: Sharpe (Train) | K27: sum
A28: GLD | B28: =AVERAGEIFS(Returns!B$3:B$1000, Returns!$A$3:$A$1000, "<="&Out_of_Sample!$C$11) -> 0.0032382798 | C28: 0.2 | D28: 0.05 | E28: 0.2 | G28: {=MMULT(TRANSPOSE($C$28:$C$37),MMULT($B$45:$K$54,$C$28:$C$37))} -> 0.00019476047 | H28: =SQRT(G28) -> 0.013955661 | I28: =SUMPRODUCT($C$28:$C$37,$B$28:$B$37) -> 0.012734211 | J28: =(I28-(H2/12))/H28 -> 0.6736247 | K28: =SUM(C28:C37) -> 1
A29: XOM | B29: =AVERAGEIFS(Returns!C$3:C$1000, Returns!$A$3:$A$1000, "<="&Out_of_Sample!$C$11) -> 0.0031638598 | C29: 0 | D29: 0 | E29: 0.1
A30: SPY | B30: =AVERAGEIFS(Returns!D$3:D$1000, Returns!$A$3:$A$1000, "<="&Out_of_Sample!$C$11) -> 0.0073986602 | C30: 0.25 | D30: 0.25 | E30: 0.4
A31: JPM | B31: =AVERAGEIFS(Returns!E$3:E$1000, Returns!$A$3:$A$1000, "<="&Out_of_Sample!$C$11) -> 0.0095077113 | C31: 0.1 | D31: 0 | E31: 0.15
A32: NVDA | B32: =AVERAGEIFS(Returns!F$3:F$1000, Returns!$A$3:$A$1000, "<="&Out_of_Sample!$C$11) -> 0.044386689 | C32: 0.15 | D32: 0 | E32: 0.15
A33: PG | B33: =AVERAGEIFS(Returns!G$3:G$1000, Returns!$A$3:$A$1000, "<="&Out_of_Sample!$C$11) -> 0.0053666132 | C33: 0.1 | D33: 0 | E33: 0.1
A34: TLT | B34: =AVERAGEIFS(Returns!H$3:H$1000, Returns!$A$3:$A$1000, "<="&Out_of_Sample!$C$11) -> -0.0025943284 | C34: 0 | D34: 0 | E34: 0.2
A35: VGT | B35: =AVERAGEIFS(Returns!I$3:I$1000, Returns!$A$3:$A$1000, "<="&Out_of_Sample!$C$11) -> 0.013824873 | C35: 0.15 | D35: 0 | E35: 0.15
A36: VNQ | B36: =AVERAGEIFS(Returns!J$3:J$1000, Returns!$A$3:$A$1000, "<="&Out_of_Sample!$C$11) -> 0.00048231539 | C36: 0 | D36: 0 | E36: 0.15
A37: VXUS | B37: =AVERAGEIFS(Returns!K$3:K$1000, Returns!$A$3:$A$1000, "<="&Out_of_Sample!$C$11) -> 0.00035447038 | C37: 0.05 | D37: 0.05 | E37: 0.2
A43: Covariance Matrix (Train)
B44: GLD | C44: XOM | D44: SPY | E44: JPM | F44: NVDA | G44: PG | H44: TLT | I44: VGT | J44: VNQ | K44: VXUS
A45: GLD | B45: {=_xlfn.COVARIANCE.P( IF(Returns!$A$3:$A$1000<=Out_of_Sample!$C$11, INDEX(Returns!$B$3:$K$1000,0, MATCH(B$44, Returns!$B$2:$K$2,0))), IF(Returns!$A$3:$A$1000<=Out_of_Sample!$C$11, INDEX(Returns!$B$3:$K$1000,0, MATCH($A45, Returns!$B$2:$K$2,0))) )} -> 0.00015352463 | C45: {=_xlfn.COVARIANCE.P( IF(Returns!$A$3:$A$1000<=Out_of_Sample!$C$11, INDEX(Returns!$B$3:$K$1000,0, MATCH(C$44, Returns!$B$2:$K$2,0))), IF(Returns!$A$3:$A$1000<=Out_of_Sample!$C$11, INDEX(Returns!$B$3:$K$1000,0, MATCH($A45, Returns!$B$2:$K$2,0))) )} -> -2.4770178e-05 | D45: {=_xlfn.COVARIANCE.P( IF(Returns!$A$3:$A$1000<=Out_of_Sample!$C$11, INDEX(Returns!$B$3:$K$1000,0, MATCH(D$44, Returns!$B$2:$K$2,0))), IF(Returns!$A$3:$A$1000<=Out_of_Sample!$C$11, INDEX(Returns!$B$3:$K$1000,0, MATCH($A45, Returns!$B$2:$K$2,0))) )} -> 1.5184674e-05 | E45: {=_xlfn.COVARIANCE.P( IF(Returns!$A$3:$A$1000<=Out_of_Sample!$C$11, INDEX(Returns!$B$3:$K$1000,0, MATCH(E$44, Returns!$B$2:$K$2,0))), IF(Returns!$A$3:$A$1000<=Out_of_Sample!$C$11, INDEX(Returns!$B$3:$K$1000,0, MATCH($A45, Returns!$B$2:$K$2,0))) )} -> -5.1627519e-05 | F45: {=_xlfn.COVARIANCE.P( IF(Returns!$A$3:$A$1000<=Out_of_Sample!$C$11, INDEX(Returns!$B$3:$K$1000,0, MATCH(F$44, Returns!$B$2:$K$2,0))), IF(Returns!$A$3:$A$1000<=Out_of_Sample!$C$11, INDEX(Returns!$B$3:$K$1000,0, MATCH($A45, Returns!$B$2:$K$2,0))) )} -> -2.034726e-05 | G45: {=_xlfn.COVARIANCE.P( IF(Returns!$A$3:$A$1000<=Out_of_Sample!$C$11, INDEX(Returns!$B$3:$K$1000,0, MATCH(G$44, Returns!$B$2:$K$2,0))), IF(Returns!$A$3:$A$1000<=Out_of_Sample!$C$11, INDEX(Returns!$B$3:$K$1000,0, MATCH($A45, Returns!$B$2:$K$2,0))) )} -> 4.8966403e-05 | H45: {=_xlfn.COVARIANCE.P( IF(Returns!$A$3:$A$1000<=Out_of_Sample!$C$11, INDEX(Returns!$B$3:$K$1000,0, MATCH(H$44, Returns!$B$2:$K$2,0))), IF(Returns!$A$3:$A$1000<=Out_of_Sample!$C$11, INDEX(Returns!$B$3:$K$1000,0, MATCH($A45, Returns!$B$2:$K$2,0))) )} -> 5.4520224e-05 | I45: {=_xlfn.COVARIANCE.P( IF(Returns!$A$3:$A$1000<=Out_of_Sample!$C$11, INDEX(Returns!$B$3:$K$1000,0, MATCH(I$44, Returns!$B$2:$K$2,0))), IF(Returns!$A$3:$A$1000<=Out_of_Sample!$C$11, INDEX(Returns!$B$3:$K$1000,0, MATCH($A45, Returns!$B$2:$K$2,0))) )} -> 1.3122402e-05 | ... K45: {=_xlfn.COVARIANCE.P( IF(Returns!$A$3:$A$1000<=Out_of_Sample!$C$11, INDEX(Returns!$B$3:$K$1000,0, MATCH(K$44, Returns!$B$2:$K$2,0))), IF(Returns!$A$3:$A$1000<=Out_of_Sample!$C$11, INDEX(Returns!$B$3:$K$1000,0, MATCH($A45, Returns!$B$2:$K$2,0))) )} -> 2.0607086e-05
A46: XOM | B46: {=_xlfn.COVARIANCE.P( IF(Returns!$A$3:$A$1000<=Out_of_Sample!$C$11, INDEX(Returns!$B$3:$K$1000,0, MATCH(B$44, Returns!$B$2:$K$2,0))), IF(Returns!$A$3:$A$1000<=Out_of_Sample!$C$11, INDEX(Returns!$B$3:$K$1000,0, MATCH($A46, Returns!$B$2:$K$2,0))) )} -> -2.4770178e-05 | C46: {=_xlfn.COVARIANCE.P( IF(Returns!$A$3:$A$1000<=Out_of_Sample!$C$11, INDEX(Returns!$B$3:$K$1000,0, MATCH(C$44, Returns!$B$2:$K$2,0))), IF(Returns!$A$3:$A$1000<=Out_of_Sample!$C$11, INDEX(Returns!$B$3:$K$1000,0, MATCH($A46, Returns!$B$2:$K$2,0))) )} -> 0.00060956078 | D46: {=_xlfn.COVARIANCE.P( IF(Returns!$A$3:$A$1000<=Out_of_Sample!$C$11, INDEX(Returns!$B$3:$K$1000,0, MATCH(D$44, Returns!$B$2:$K$2,0))), IF(Returns!$A$3:$A$1000<=Out_of_Sample!$C$11, INDEX(Returns!$B$3:$K$1000,0, MATCH($A46, Returns!$B$2:$K$2,0))) )} -> 0.00019561779 | E46: {=_xlfn.COVARIANCE.P( IF(Returns!$A$3:$A$1000<=Out_of_Sample!$C$11, INDEX(Returns!$B$3:$K$1000,0, MATCH(E$44, Returns!$B$2:$K$2,0))), IF(Returns!$A$3:$A$1000<=Out_of_Sample!$C$11, INDEX(Returns!$B$3:$K$1000,0, MATCH($A46, Returns!$B$2:$K$2,0))) )} -> 0.00027664457 | F46: {=_xlfn.COVARIANCE.P( IF(Returns!$A$3:$A$1000<=Out_of_Sample!$C$11, INDEX(Returns!$B$3:$K$1000,0, MATCH(F$44, Returns!$B$2:$K$2,0))), IF(Returns!$A$3:$A$1000<=Out_of_Sample!$C$11, INDEX(Returns!$B$3:$K$1000,0, MATCH($A46, Returns!$B$2:$K$2,0))) )} -> 0.00018862721 | G46: {=_xlfn.COVARIANCE.P( IF(Returns!$A$3:$A$1000<=Out_of_Sample!$C$11, INDEX(Returns!$B$3:$K$1000,0, MATCH(G$44, Returns!$B$2:$K$2,0))), IF(Returns!$A$3:$A$1000<=Out_of_Sample!$C$11, INDEX(Returns!$B$3:$K$1000,0, MATCH($A46, Returns!$B$2:$K$2,0))) )} -> 3.45399e-05 | H46: {=_xlfn.COVARIANCE.P( IF(Returns!$A$3:$A$1000<=Out_of_Sample!$C$11, INDEX(Returns!$B$3:$K$1000,0, MATCH(H$44, Returns!$B$2:$K$2,0))), IF(Returns!$A$3:$A$1000<=Out_of_Sample!$C$11, INDEX(Returns!$B$3:$K$1000,0, MATCH($A46, Returns!$B$2:$K$2,0))) )} -> -8.767544e-05 | I46: {=_xlfn.COVARIANCE.P( IF(Returns!$A$3:$A$1000<=Out_of_Sample!$C$11, INDEX(Returns!$B$3:$K$1000,0, MATCH(I$44, Returns!$B$2:$K$2,0))), IF(Returns!$A$3:$A$1000<=Out_of_Sample!$C$11, INDEX(Returns!$B$3:$K$1000,0, MATCH($A46, Returns!$B$2:$K$2,0))) )} -> 0.00017885689 | ... K46: {=_xlfn.COVARIANCE.P( IF(Returns!$A$3:$A$1000<=Out_of_Sample!$C$11, INDEX(Returns!$B$3:$K$1000,0, MATCH(K$44, Returns!$B$2:$K$2,0))), IF(Returns!$A$3:$A$1000<=Out_of_Sample!$C$11, INDEX(Returns!$B$3:$K$1000,0, MATCH($A46, Returns!$B$2:$K$2,0))) )} -> 0.00018833709
A47: SPY | B47: {=_xlfn.COVARIANCE.P( IF(Returns!$A$3:$A$1000<=Out_of_Sample!$C$11, INDEX(Returns!$B$3:$K$1000,0, MATCH(B$44, Returns!$B$2:$K$2,0))), IF(Returns!$A$3:$A$1000<=Out_of_Sample!$C$11, INDEX(Returns!$B$3:$K$1000,0, MATCH($A47, Returns!$B$2:$K$2,0))) )} -> 1.5184674e-05 | C47: {=_xlfn.COVARIANCE.P( IF(Returns!$A$3:$A$1000<=Out_of_Sample!$C$11, INDEX(Returns!$B$3:$K$1000,0, MATCH(C$44, Returns!$B$2:$K$2,0))), IF(Returns!$A$3:$A$1000<=Out_of_Sample!$C$11, INDEX(Returns!$B$3:$K$1000,0, MATCH($A47, Returns!$B$2:$K$2,0))) )} -> 0.00019561779 | D47: {=_xlfn.COVARIANCE.P( IF(Returns!$A$3:$A$1000<=Out_of_Sample!$C$11, INDEX(Returns!$B$3:$K$1000,0, MATCH(D$44, Returns!$B$2:$K$2,0))), IF(Returns!$A$3:$A$1000<=Out_of_Sample!$C$11, INDEX(Returns!$B$3:$K$1000,0, MATCH($A47, Returns!$B$2:$K$2,0))) )} -> 0.00020392375 | E47: {=_xlfn.COVARIANCE.P( IF(Returns!$A$3:$A$1000<=Out_of_Sample!$C$11, INDEX(Returns!$B$3:$K$1000,0, MATCH(E$44, Returns!$B$2:$K$2,0))), IF(Returns!$A$3:$A$1000<=Out_of_Sample!$C$11, INDEX(Returns!$B$3:$K$1000,0, MATCH($A47, Returns!$B$2:$K$2,0))) )} -> 0.00022243061 | F47: {=_xlfn.COVARIANCE.P( IF(Returns!$A$3:$A$1000<=Out_of_Sample!$C$11, INDEX(Returns!$B$3:$K$1000,0, MATCH(F$44, Returns!$B$2:$K$2,0))), IF(Returns!$A$3:$A$1000<=Out_of_Sample!$C$11, INDEX(Returns!$B$3:$K$1000,0, MATCH($A47, Returns!$B$2:$K$2,0))) )} -> 0.00036018944 | G47: {=_xlfn.COVARIANCE.P( IF(Returns!$A$3:$A$1000<=Out_of_Sample!$C$11, INDEX(Returns!$B$3:$K$1000,0, MATCH(G$44, Returns!$B$2:$K$2,0))), IF(Returns!$A$3:$A$1000<=Out_of_Sample!$C$11, INDEX(Returns!$B$3:$K$1000,0, MATCH($A47, Returns!$B$2:$K$2,0))) )} -> 7.6256292e-05 | H47: {=_xlfn.COVARIANCE.P( IF(Returns!$A$3:$A$1000<=Out_of_Sample!$C$11, INDEX(Returns!$B$3:$K$1000,0, MATCH(H$44, Returns!$B$2:$K$2,0))), IF(Returns!$A$3:$A$1000<=Out_of_Sample!$C$11, INDEX(Returns!$B$3:$K$1000,0, MATCH($A47, Returns!$B$2:$K$2,0))) )} -> -6.807137e-06 | I47: {=_xlfn.COVARIANCE.P( IF(Returns!$A$3:$A$1000<=Out_of_Sample!$C$11, INDEX(Returns!$B$3:$K$1000,0, MATCH(I$44, Returns!$B$2:$K$2,0))), IF(Returns!$A$3:$A$1000<=Out_of_Sample!$C$11, INDEX(Returns!$B$3:$K$1000,0, MATCH($A47, Returns!$B$2:$K$2,0))) )} -> 0.00023982609 | ... K47: {=_xlfn.COVARIANCE.P( IF(Returns!$A$3:$A$1000<=Out_of_Sample!$C$11, INDEX(Returns!$B$3:$K$1000,0, MATCH(K$44, Returns!$B$2:$K$2,0))), IF(Returns!$A$3:$A$1000<=Out_of_Sample!$C$11, INDEX(Returns!$B$3:$K$1000,0, MATCH($A47, Returns!$B$2:$K$2,0))) )} -> 0.00017013345
A48: JPM | B48: {=_xlfn.COVARIANCE.P( IF(Returns!$A$3:$A$1000<=Out_of_Sample!$C$11, INDEX(Returns!$B$3:$K$1000,0, MATCH(B$44, Returns!$B$2:$K$2,0))), IF(Returns!$A$3:$A$1000<=Out_of_Sample!$C$11, INDEX(Returns!$B$3:$K$1000,0, MATCH($A48, Returns!$B$2:$K$2,0))) )} -> -5.1627519e-05 | C48: {=_xlfn.COVARIANCE.P( IF(Returns!$A$3:$A$1000<=Out_of_Sample!$C$11, INDEX(Returns!$B$3:$K$1000,0, MATCH(C$44, Returns!$B$2:$K$2,0))), IF(Returns!$A$3:$A$1000<=Out_of_Sample!$C$11, INDEX(Returns!$B$3:$K$1000,0, MATCH($A48, Returns!$B$2:$K$2,0))) )} -> 0.00027664457 | D48: {=_xlfn.COVARIANCE.P( IF(Returns!$A$3:$A$1000<=Out_of_Sample!$C$11, INDEX(Returns!$B$3:$K$1000,0, MATCH(D$44, Returns!$B$2:$K$2,0))), IF(Returns!$A$3:$A$1000<=Out_of_Sample!$C$11, INDEX(Returns!$B$3:$K$1000,0, MATCH($A48, Returns!$B$2:$K$2,0))) )} -> 0.00022243061 | E48: {=_xlfn.COVARIANCE.P( IF(Returns!$A$3:$A$1000<=Out_of_Sample!$C$11, INDEX(Returns!$B$3:$K$1000,0, MATCH(E$44, Returns!$B$2:$K$2,0))), IF(Returns!$A$3:$A$1000<=Out_of_Sample!$C$11, INDEX(Returns!$B$3:$K$1000,0, MATCH($A48, Returns!$B$2:$K$2,0))) )} -> 0.00046076334 | F48: {=_xlfn.COVARIANCE.P( IF(Returns!$A$3:$A$1000<=Out_of_Sample!$C$11, INDEX(Returns!$B$3:$K$1000,0, MATCH(F$44, Returns!$B$2:$K$2,0))), IF(Returns!$A$3:$A$1000<=Out_of_Sample!$C$11, INDEX(Returns!$B$3:$K$1000,0, MATCH($A48, Returns!$B$2:$K$2,0))) )} -> 0.00032878422 | G48: {=_xlfn.COVARIANCE.P( IF(Returns!$A$3:$A$1000<=Out_of_Sample!$C$11, INDEX(Returns!$B$3:$K$1000,0, MATCH(G$44, Returns!$B$2:$K$2,0))), IF(Returns!$A$3:$A$1000<=Out_of_Sample!$C$11, INDEX(Returns!$B$3:$K$1000,0, MATCH($A48, Returns!$B$2:$K$2,0))) )} -> 3.3809549e-05 | H48: {=_xlfn.COVARIANCE.P( IF(Returns!$A$3:$A$1000<=Out_of_Sample!$C$11, INDEX(Returns!$B$3:$K$1000,0, MATCH(H$44, Returns!$B$2:$K$2,0))), IF(Returns!$A$3:$A$1000<=Out_of_Sample!$C$11, INDEX(Returns!$B$3:$K$1000,0, MATCH($A48, Returns!$B$2:$K$2,0))) )} -> -9.0153235e-05 | I48: {=_xlfn.COVARIANCE.P( IF(Returns!$A$3:$A$1000<=Out_of_Sample!$C$11, INDEX(Returns!$B$3:$K$1000,0, MATCH(I$44, Returns!$B$2:$K$2,0))), IF(Returns!$A$3:$A$1000<=Out_of_Sample!$C$11, INDEX(Returns!$B$3:$K$1000,0, MATCH($A48, Returns!$B$2:$K$2,0))) )} -> 0.00022580448 | ... K48: {=_xlfn.COVARIANCE.P( IF(Returns!$A$3:$A$1000<=Out_of_Sample!$C$11, INDEX(Returns!$B$3:$K$1000,0, MATCH(K$44, Returns!$B$2:$K$2,0))), IF(Returns!$A$3:$A$1000<=Out_of_Sample!$C$11, INDEX(Returns!$B$3:$K$1000,0, MATCH($A48, Returns!$B$2:$K$2,0))) )} -> 0.00021028178
A49: NVDA | B49: {=_xlfn.COVARIANCE.P( IF(Returns!$A$3:$A$1000<=Out_of_Sample!$C$11, INDEX(Returns!$B$3:$K$1000,0, MATCH(B$44, Returns!$B$2:$K$2,0))), IF(Returns!$A$3:$A$1000<=Out_of_Sample!$C$11, INDEX(Returns!$B$3:$K$1000,0, MATCH($A49, Returns!$B$2:$K$2,0))) )} -> -2.034726e-05 | C49: {=_xlfn.COVARIANCE.P( IF(Returns!$A$3:$A$1000<=Out_of_Sample!$C$11, INDEX(Returns!$B$3:$K$1000,0, MATCH(C$44, Returns!$B$2:$K$2,0))), IF(Returns!$A$3:$A$1000<=Out_of_Sample!$C$11, INDEX(Returns!$B$3:$K$1000,0, MATCH($A49, Returns!$B$2:$K$2,0))) )} -> 0.00018862721 | D49: {=_xlfn.COVARIANCE.P( IF(Returns!$A$3:$A$1000<=Out_of_Sample!$C$11, INDEX(Returns!$B$3:$K$1000,0, MATCH(D$44, Returns!$B$2:$K$2,0))), IF(Returns!$A$3:$A$1000<=Out_of_Sample!$C$11, INDEX(Returns!$B$3:$K$1000,0, MATCH($A49, Returns!$B$2:$K$2,0))) )} -> 0.00036018944 | E49: {=_xlfn.COVARIANCE.P( IF(Returns!$A$3:$A$1000<=Out_of_Sample!$C$11, INDEX(Returns!$B$3:$K$1000,0, MATCH(E$44, Returns!$B$2:$K$2,0))), IF(Returns!$A$3:$A$1000<=Out_of_Sample!$C$11, INDEX(Returns!$B$3:$K$1000,0, MATCH($A49, Returns!$B$2:$K$2,0))) )} -> 0.00032878422 | F49: {=_xlfn.COVARIANCE.P( IF(Returns!$A$3:$A$1000<=Out_of_Sample!$C$11, INDEX(Returns!$B$3:$K$1000,0, MATCH(F$44, Returns!$B$2:$K$2,0))), IF(Returns!$A$3:$A$1000<=Out_of_Sample!$C$11, INDEX(Returns!$B$3:$K$1000,0, MATCH($A49, Returns!$B$2:$K$2,0))) )} -> 0.0018373677 | G49: {=_xlfn.COVARIANCE.P( IF(Returns!$A$3:$A$1000<=Out_of_Sample!$C$11, INDEX(Returns!$B$3:$K$1000,0, MATCH(G$44, Returns!$B$2:$K$2,0))), IF(Returns!$A$3:$A$1000<=Out_of_Sample!$C$11, INDEX(Returns!$B$3:$K$1000,0, MATCH($A49, Returns!$B$2:$K$2,0))) )} -> 1.2817613e-05 | H49: {=_xlfn.COVARIANCE.P( IF(Returns!$A$3:$A$1000<=Out_of_Sample!$C$11, INDEX(Returns!$B$3:$K$1000,0, MATCH(H$44, Returns!$B$2:$K$2,0))), IF(Returns!$A$3:$A$1000<=Out_of_Sample!$C$11, INDEX(Returns!$B$3:$K$1000,0, MATCH($A49, Returns!$B$2:$K$2,0))) )} -> 3.0054558e-05 | I49: {=_xlfn.COVARIANCE.P( IF(Returns!$A$3:$A$1000<=Out_of_Sample!$C$11, INDEX(Returns!$B$3:$K$1000,0, MATCH(I$44, Returns!$B$2:$K$2,0))), IF(Returns!$A$3:$A$1000<=Out_of_Sample!$C$11, INDEX(Returns!$B$3:$K$1000,0, MATCH($A49, Returns!$B$2:$K$2,0))) )} -> 0.00055483115 | ... K49: {=_xlfn.COVARIANCE.P( IF(Returns!$A$3:$A$1000<=Out_of_Sample!$C$11, INDEX(Returns!$B$3:$K$1000,0, MATCH(K$44, Returns!$B$2:$K$2,0))), IF(Returns!$A$3:$A$1000<=Out_of_Sample!$C$11, INDEX(Returns!$B$3:$K$1000,0, MATCH($A49, Returns!$B$2:$K$2,0))) )} -> 0.00026170033
A50: PG | B50: {=_xlfn.COVARIANCE.P( IF(Returns!$A$3:$A$1000<=Out_of_Sample!$C$11, INDEX(Returns!$B$3:$K$1000,0, MATCH(B$44, Returns!$B$2:$K$2,0))), IF(Returns!$A$3:$A$1000<=Out_of_Sample!$C$11, INDEX(Returns!$B$3:$K$1000,0, MATCH($A50, Returns!$B$2:$K$2,0))) )} -> 4.8966403e-05 | C50: {=_xlfn.COVARIANCE.P( IF(Returns!$A$3:$A$1000<=Out_of_Sample!$C$11, INDEX(Returns!$B$3:$K$1000,0, MATCH(C$44, Returns!$B$2:$K$2,0))), IF(Returns!$A$3:$A$1000<=Out_of_Sample!$C$11, INDEX(Returns!$B$3:$K$1000,0, MATCH($A50, Returns!$B$2:$K$2,0))) )} -> 3.45399e-05 | D50: {=_xlfn.COVARIANCE.P( IF(Returns!$A$3:$A$1000<=Out_of_Sample!$C$11, INDEX(Returns!$B$3:$K$1000,0, MATCH(D$44, Returns!$B$2:$K$2,0))), IF(Returns!$A$3:$A$1000<=Out_of_Sample!$C$11, INDEX(Returns!$B$3:$K$1000,0, MATCH($A50, Returns!$B$2:$K$2,0))) )} -> 7.6256292e-05 | E50: {=_xlfn.COVARIANCE.P( IF(Returns!$A$3:$A$1000<=Out_of_Sample!$C$11, INDEX(Returns!$B$3:$K$1000,0, MATCH(E$44, Returns!$B$2:$K$2,0))), IF(Returns!$A$3:$A$1000<=Out_of_Sample!$C$11, INDEX(Returns!$B$3:$K$1000,0, MATCH($A50, Returns!$B$2:$K$2,0))) )} -> 3.3809549e-05 | F50: {=_xlfn.COVARIANCE.P( IF(Returns!$A$3:$A$1000<=Out_of_Sample!$C$11, INDEX(Returns!$B$3:$K$1000,0, MATCH(F$44, Returns!$B$2:$K$2,0))), IF(Returns!$A$3:$A$1000<=Out_of_Sample!$C$11, INDEX(Returns!$B$3:$K$1000,0, MATCH($A50, Returns!$B$2:$K$2,0))) )} -> 1.2817613e-05 | G50: {=_xlfn.COVARIANCE.P( IF(Returns!$A$3:$A$1000<=Out_of_Sample!$C$11, INDEX(Returns!$B$3:$K$1000,0, MATCH(G$44, Returns!$B$2:$K$2,0))), IF(Returns!$A$3:$A$1000<=Out_of_Sample!$C$11, INDEX(Returns!$B$3:$K$1000,0, MATCH($A50, Returns!$B$2:$K$2,0))) )} -> 0.00018840614 | H50: {=_xlfn.COVARIANCE.P( IF(Returns!$A$3:$A$1000<=Out_of_Sample!$C$11, INDEX(Returns!$B$3:$K$1000,0, MATCH(H$44, Returns!$B$2:$K$2,0))), IF(Returns!$A$3:$A$1000<=Out_of_Sample!$C$11, INDEX(Returns!$B$3:$K$1000,0, MATCH($A50, Returns!$B$2:$K$2,0))) )} -> 1.9615343e-05 | I50: {=_xlfn.COVARIANCE.P( IF(Returns!$A$3:$A$1000<=Out_of_Sample!$C$11, INDEX(Returns!$B$3:$K$1000,0, MATCH(I$44, Returns!$B$2:$K$2,0))), IF(Returns!$A$3:$A$1000<=Out_of_Sample!$C$11, INDEX(Returns!$B$3:$K$1000,0, MATCH($A50, Returns!$B$2:$K$2,0))) )} -> 8.0262962e-05 | ... K50: {=_xlfn.COVARIANCE.P( IF(Returns!$A$3:$A$1000<=Out_of_Sample!$C$11, INDEX(Returns!$B$3:$K$1000,0, MATCH(K$44, Returns!$B$2:$K$2,0))), IF(Returns!$A$3:$A$1000<=Out_of_Sample!$C$11, INDEX(Returns!$B$3:$K$1000,0, MATCH($A50, Returns!$B$2:$K$2,0))) )} -> 5.5079295e-05
A51: TLT | B51: {=_xlfn.COVARIANCE.P( IF(Returns!$A$3:$A$1000<=Out_of_Sample!$C$11, INDEX(Returns!$B$3:$K$1000,0, MATCH(B$44, Returns!$B$2:$K$2,0))), IF(Returns!$A$3:$A$1000<=Out_of_Sample!$C$11, INDEX(Returns!$B$3:$K$1000,0, MATCH($A51, Returns!$B$2:$K$2,0))) )} -> 5.4520224e-05 | C51: {=_xlfn.COVARIANCE.P( IF(Returns!$A$3:$A$1000<=Out_of_Sample!$C$11, INDEX(Returns!$B$3:$K$1000,0, MATCH(C$44, Returns!$B$2:$K$2,0))), IF(Returns!$A$3:$A$1000<=Out_of_Sample!$C$11, INDEX(Returns!$B$3:$K$1000,0, MATCH($A51, Returns!$B$2:$K$2,0))) )} -> -8.767544e-05 | D51: {=_xlfn.COVARIANCE.P( IF(Returns!$A$3:$A$1000<=Out_of_Sample!$C$11, INDEX(Returns!$B$3:$K$1000,0, MATCH(D$44, Returns!$B$2:$K$2,0))), IF(Returns!$A$3:$A$1000<=Out_of_Sample!$C$11, INDEX(Returns!$B$3:$K$1000,0, MATCH($A51, Returns!$B$2:$K$2,0))) )} -> -6.807137e-06 | E51: {=_xlfn.COVARIANCE.P( IF(Returns!$A$3:$A$1000<=Out_of_Sample!$C$11, INDEX(Returns!$B$3:$K$1000,0, MATCH(E$44, Returns!$B$2:$K$2,0))), IF(Returns!$A$3:$A$1000<=Out_of_Sample!$C$11, INDEX(Returns!$B$3:$K$1000,0, MATCH($A51, Returns!$B$2:$K$2,0))) )} -> -9.0153235e-05 | F51: {=_xlfn.COVARIANCE.P( IF(Returns!$A$3:$A$1000<=Out_of_Sample!$C$11, INDEX(Returns!$B$3:$K$1000,0, MATCH(F$44, Returns!$B$2:$K$2,0))), IF(Returns!$A$3:$A$1000<=Out_of_Sample!$C$11, INDEX(Returns!$B$3:$K$1000,0, MATCH($A51, Returns!$B$2:$K$2,0))) )} -> 3.0054558e-05 | G51: {=_xlfn.COVARIANCE.P( IF(Returns!$A$3:$A$1000<=Out_of_Sample!$C$11, INDEX(Returns!$B$3:$K$1000,0, MATCH(G$44, Returns!$B$2:$K$2,0))), IF(Returns!$A$3:$A$1000<=Out_of_Sample!$C$11, INDEX(Returns!$B$3:$K$1000,0, MATCH($A51, Returns!$B$2:$K$2,0))) )} -> 1.9615343e-05 | H51: {=_xlfn.COVARIANCE.P( IF(Returns!$A$3:$A$1000<=Out_of_Sample!$C$11, INDEX(Returns!$B$3:$K$1000,0, MATCH(H$44, Returns!$B$2:$K$2,0))), IF(Returns!$A$3:$A$1000<=Out_of_Sample!$C$11, INDEX(Returns!$B$3:$K$1000,0, MATCH($A51, Returns!$B$2:$K$2,0))) )} -> 0.0001274467 | I51: {=_xlfn.COVARIANCE.P( IF(Returns!$A$3:$A$1000<=Out_of_Sample!$C$11, INDEX(Returns!$B$3:$K$1000,0, MATCH(I$44, Returns!$B$2:$K$2,0))), IF(Returns!$A$3:$A$1000<=Out_of_Sample!$C$11, INDEX(Returns!$B$3:$K$1000,0, MATCH($A51, Returns!$B$2:$K$2,0))) )} -> 1.0858861e-05 | ... K51: {=_xlfn.COVARIANCE.P( IF(Returns!$A$3:$A$1000<=Out_of_Sample!$C$11, INDEX(Returns!$B$3:$K$1000,0, MATCH(K$44, Returns!$B$2:$K$2,0))), IF(Returns!$A$3:$A$1000<=Out_of_Sample!$C$11, INDEX(Returns!$B$3:$K$1000,0, MATCH($A51, Returns!$B$2:$K$2,0))) )} -> -1.3767191e-05
A52: VGT | B52: {=_xlfn.COVARIANCE.P( IF(Returns!$A$3:$A$1000<=Out_of_Sample!$C$11, INDEX(Returns!$B$3:$K$1000,0, MATCH(B$44, Returns!$B$2:$K$2,0))), IF(Returns!$A$3:$A$1000<=Out_of_Sample!$C$11, INDEX(Returns!$B$3:$K$1000,0, MATCH($A52, Returns!$B$2:$K$2,0))) )} -> 1.3122402e-05 | C52: {=_xlfn.COVARIANCE.P( IF(Returns!$A$3:$A$1000<=Out_of_Sample!$C$11, INDEX(Returns!$B$3:$K$1000,0, MATCH(C$44, Returns!$B$2:$K$2,0))), IF(Returns!$A$3:$A$1000<=Out_of_Sample!$C$11, INDEX(Returns!$B$3:$K$1000,0, MATCH($A52, Returns!$B$2:$K$2,0))) )} -> 0.00017885689 | D52: {=_xlfn.COVARIANCE.P( IF(Returns!$A$3:$A$1000<=Out_of_Sample!$C$11, INDEX(Returns!$B$3:$K$1000,0, MATCH(D$44, Returns!$B$2:$K$2,0))), IF(Returns!$A$3:$A$1000<=Out_of_Sample!$C$11, INDEX(Returns!$B$3:$K$1000,0, MATCH($A52, Returns!$B$2:$K$2,0))) )} -> 0.00023982609 | E52: {=_xlfn.COVARIANCE.P( IF(Returns!$A$3:$A$1000<=Out_of_Sample!$C$11, INDEX(Returns!$B$3:$K$1000,0, MATCH(E$44, Returns!$B$2:$K$2,0))), IF(Returns!$A$3:$A$1000<=Out_of_Sample!$C$11, INDEX(Returns!$B$3:$K$1000,0, MATCH($A52, Returns!$B$2:$K$2,0))) )} -> 0.00022580448 | F52: {=_xlfn.COVARIANCE.P( IF(Returns!$A$3:$A$1000<=Out_of_Sample!$C$11, INDEX(Returns!$B$3:$K$1000,0, MATCH(F$44, Returns!$B$2:$K$2,0))), IF(Returns!$A$3:$A$1000<=Out_of_Sample!$C$11, INDEX(Returns!$B$3:$K$1000,0, MATCH($A52, Returns!$B$2:$K$2,0))) )} -> 0.00055483115 | G52: {=_xlfn.COVARIANCE.P( IF(Returns!$A$3:$A$1000<=Out_of_Sample!$C$11, INDEX(Returns!$B$3:$K$1000,0, MATCH(G$44, Returns!$B$2:$K$2,0))), IF(Returns!$A$3:$A$1000<=Out_of_Sample!$C$11, INDEX(Returns!$B$3:$K$1000,0, MATCH($A52, Returns!$B$2:$K$2,0))) )} -> 8.0262962e-05 | H52: {=_xlfn.COVARIANCE.P( IF(Returns!$A$3:$A$1000<=Out_of_Sample!$C$11, INDEX(Returns!$B$3:$K$1000,0, MATCH(H$44, Returns!$B$2:$K$2,0))), IF(Returns!$A$3:$A$1000<=Out_of_Sample!$C$11, INDEX(Returns!$B$3:$K$1000,0, MATCH($A52, Returns!$B$2:$K$2,0))) )} -> 1.0858861e-05 | I52: {=_xlfn.COVARIANCE.P( IF(Returns!$A$3:$A$1000<=Out_of_Sample!$C$11, INDEX(Returns!$B$3:$K$1000,0, MATCH(I$44, Returns!$B$2:$K$2,0))), IF(Returns!$A$3:$A$1000<=Out_of_Sample!$C$11, INDEX(Returns!$B$3:$K$1000,0, MATCH($A52, Returns!$B$2:$K$2,0))) )} -> 0.00033098015 | ... K52: {=_xlfn.COVARIANCE.P( IF(Returns!$A$3:$A$1000<=Out_of_Sample!$C$11, INDEX(Returns!$B$3:$K$1000,0, MATCH(K$44, Returns!$B$2:$K$2,0))), IF(Returns!$A$3:$A$1000<=Out_of_Sample!$C$11, INDEX(Returns!$B$3:$K$1000,0, MATCH($A52, Returns!$B$2:$K$2,0))) )} -> 0.00019347994
A53: VNQ | B53: {=_xlfn.COVARIANCE.P( IF(Returns!$A$3:$A$1000<=Out_of_Sample!$C$11, INDEX(Returns!$B$3:$K$1000,0, MATCH(B$44, Returns!$B$2:$K$2,0))), IF(Returns!$A$3:$A$1000<=Out_of_Sample!$C$11, INDEX(Returns!$B$3:$K$1000,0, MATCH($A53, Returns!$B$2:$K$2,0))) )} -> 2.8189962e-05 | C53: {=_xlfn.COVARIANCE.P( IF(Returns!$A$3:$A$1000<=Out_of_Sample!$C$11, INDEX(Returns!$B$3:$K$1000,0, MATCH(C$44, Returns!$B$2:$K$2,0))), IF(Returns!$A$3:$A$1000<=Out_of_Sample!$C$11, INDEX(Returns!$B$3:$K$1000,0, MATCH($A53, Returns!$B$2:$K$2,0))) )} -> 0.00016981182 | D53: {=_xlfn.COVARIANCE.P( IF(Returns!$A$3:$A$1000<=Out_of_Sample!$C$11, INDEX(Returns!$B$3:$K$1000,0, MATCH(D$44, Returns!$B$2:$K$2,0))), IF(Returns!$A$3:$A$1000<=Out_of_Sample!$C$11, INDEX(Returns!$B$3:$K$1000,0, MATCH($A53, Returns!$B$2:$K$2,0))) )} -> 0.00017168973 | E53: {=_xlfn.COVARIANCE.P( IF(Returns!$A$3:$A$1000<=Out_of_Sample!$C$11, INDEX(Returns!$B$3:$K$1000,0, MATCH(E$44, Returns!$B$2:$K$2,0))), IF(Returns!$A$3:$A$1000<=Out_of_Sample!$C$11, INDEX(Returns!$B$3:$K$1000,0, MATCH($A53, Returns!$B$2:$K$2,0))) )} -> 0.00014352842 | F53: {=_xlfn.COVARIANCE.P( IF(Returns!$A$3:$A$1000<=Out_of_Sample!$C$11, INDEX(Returns!$B$3:$K$1000,0, MATCH(F$44, Returns!$B$2:$K$2,0))), IF(Returns!$A$3:$A$1000<=Out_of_Sample!$C$11, INDEX(Returns!$B$3:$K$1000,0, MATCH($A53, Returns!$B$2:$K$2,0))) )} -> 0.00019780026 | G53: {=_xlfn.COVARIANCE.P( IF(Returns!$A$3:$A$1000<=Out_of_Sample!$C$11, INDEX(Returns!$B$3:$K$1000,0, MATCH(G$44, Returns!$B$2:$K$2,0))), IF(Returns!$A$3:$A$1000<=Out_of_Sample!$C$11, INDEX(Returns!$B$3:$K$1000,0, MATCH($A53, Returns!$B$2:$K$2,0))) )} -> 0.00010811454 | H53: {=_xlfn.COVARIANCE.P( IF(Returns!$A$3:$A$1000<=Out_of_Sample!$C$11, INDEX(Returns!$B$3:$K$1000,0, MATCH(H$44, Returns!$B$2:$K$2,0))), IF(Returns!$A$3:$A$1000<=Out_of_Sample!$C$11, INDEX(Returns!$B$3:$K$1000,0, MATCH($A53, Returns!$B$2:$K$2,0))) )} -> 4.2046183e-05 | I53: {=_xlfn.COVARIANCE.P( IF(Returns!$A$3:$A$1000<=Out_of_Sample!$C$11, INDEX(Returns!$B$3:$K$1000,0, MATCH(I$44, Returns!$B$2:$K$2,0))), IF(Returns!$A$3:$A$1000<=Out_of_Sample!$C$11, INDEX(Returns!$B$3:$K$1000,0, MATCH($A53, Returns!$B$2:$K$2,0))) )} -> 0.00018357265 | ... K53: {=_xlfn.COVARIANCE.P( IF(Returns!$A$3:$A$1000<=Out_of_Sample!$C$11, INDEX(Returns!$B$3:$K$1000,0, MATCH(K$44, Returns!$B$2:$K$2,0))), IF(Returns!$A$3:$A$1000<=Out_of_Sample!$C$11, INDEX(Returns!$B$3:$K$1000,0, MATCH($A53, Returns!$B$2:$K$2,0))) )} -> 0.00014144281
A54: VXUS | B54: {=_xlfn.COVARIANCE.P( IF(Returns!$A$3:$A$1000<=Out_of_Sample!$C$11, INDEX(Returns!$B$3:$K$1000,0, MATCH(B$44, Returns!$B$2:$K$2,0))), IF(Returns!$A$3:$A$1000<=Out_of_Sample!$C$11, INDEX(Returns!$B$3:$K$1000,0, MATCH($A54, Returns!$B$2:$K$2,0))) )} -> 2.0607086e-05 | C54: {=_xlfn.COVARIANCE.P( IF(Returns!$A$3:$A$1000<=Out_of_Sample!$C$11, INDEX(Returns!$B$3:$K$1000,0, MATCH(C$44, Returns!$B$2:$K$2,0))), IF(Returns!$A$3:$A$1000<=Out_of_Sample!$C$11, INDEX(Returns!$B$3:$K$1000,0, MATCH($A54, Returns!$B$2:$K$2,0))) )} -> 0.00018833709 | D54: {=_xlfn.COVARIANCE.P( IF(Returns!$A$3:$A$1000<=Out_of_Sample!$C$11, INDEX(Returns!$B$3:$K$1000,0, MATCH(D$44, Returns!$B$2:$K$2,0))), IF(Returns!$A$3:$A$1000<=Out_of_Sample!$C$11, INDEX(Returns!$B$3:$K$1000,0, MATCH($A54, Returns!$B$2:$K$2,0))) )} -> 0.00017013345 | E54: {=_xlfn.COVARIANCE.P( IF(Returns!$A$3:$A$1000<=Out_of_Sample!$C$11, INDEX(Returns!$B$3:$K$1000,0, MATCH(E$44, Returns!$B$2:$K$2,0))), IF(Returns!$A$3:$A$1000<=Out_of_Sample!$C$11, INDEX(Returns!$B$3:$K$1000,0, MATCH($A54, Returns!$B$2:$K$2,0))) )} -> 0.00021028178 | F54: {=_xlfn.COVARIANCE.P( IF(Returns!$A$3:$A$1000<=Out_of_Sample!$C$11, INDEX(Returns!$B$3:$K$1000,0, MATCH(F$44, Returns!$B$2:$K$2,0))), IF(Returns!$A$3:$A$1000<=Out_of_Sample!$C$11, INDEX(Returns!$B$3:$K$1000,0, MATCH($A54, Returns!$B$2:$K$2,0))) )} -> 0.00026170033 | G54: {=_xlfn.COVARIANCE.P( IF(Returns!$A$3:$A$1000<=Out_of_Sample!$C$11, INDEX(Returns!$B$3:$K$1000,0, MATCH(G$44, Returns!$B$2:$K$2,0))), IF(Returns!$A$3:$A$1000<=Out_of_Sample!$C$11, INDEX(Returns!$B$3:$K$1000,0, MATCH($A54, Returns!$B$2:$K$2,0))) )} -> 5.5079295e-05 | H54: {=_xlfn.COVARIANCE.P( IF(Returns!$A$3:$A$1000<=Out_of_Sample!$C$11, INDEX(Returns!$B$3:$K$1000,0, MATCH(H$44, Returns!$B$2:$K$2,0))), IF(Returns!$A$3:$A$1000<=Out_of_Sample!$C$11, INDEX(Returns!$B$3:$K$1000,0, MATCH($A54, Returns!$B$2:$K$2,0))) )} -> -1.3767191e-05 | I54: {=_xlfn.COVARIANCE.P( IF(Returns!$A$3:$A$1000<=Out_of_Sample!$C$11, INDEX(Returns!$B$3:$K$1000,0, MATCH(I$44, Returns!$B$2:$K$2,0))), IF(Returns!$A$3:$A$1000<=Out_of_Sample!$C$11, INDEX(Returns!$B$3:$K$1000,0, MATCH($A54, Returns!$B$2:$K$2,0))) )} -> 0.00019347994 | ... K54: {=_xlfn.COVARIANCE.P( IF(Returns!$A$3:$A$1000<=Out_of_Sample!$C$11, INDEX(Returns!$B$3:$K$1000,0, MATCH(K$44, Returns!$B$2:$K$2,0))), IF(Returns!$A$3:$A$1000<=Out_of_Sample!$C$11, INDEX(Returns!$B$3:$K$1000,0, MATCH($A54, Returns!$B$2:$K$2,0))) )} -> 0.00018409091

Sheet Solver_Comparison
A1: Portfolio Optimization – Unconstrained vs Constrained
A11: Unconstrainded Model | L11: Constrained Model
B14: Asset | C14: Weight | F14: Expected Return | G14: Sharp | H14: Volatility | M14: Asset | N14: Weight | Q14: Expected Return | R14: Sharp | S14: Volatility
B15: GLD | C15: 0.54727927 | F15: 0.29666048 | G15: 1.5339886 | H15: 0.16731575 | M15: GLD | N15: 0.2 | Q15: 0.21181041 | R15: 1.1705843 | S15: 0.14677321
B16: XOM | C16: 0 | M16: XOM | N16: 0
B17: SPY | C17: 0 | H17: ` | M17: SPY | N17: 0.25
B18: JPM | C18: 0.14345988 | M18: JPM | N18: 0.15 | Q18: Constraints
B19: NVDA | C19: 0.30926084 | M19: NVDA | N19: 0.15 | Q19: Asset | R19: Min Weight | S19: Max Weight
B20: PG | C20: 0 | M20: PG | N20: 0.1 | Q20: GLD | R20: 0.05 | S20: 0.2
B21: TLT | C21: 0 | M21: TLT | N21: 0 | Q21: XOM | R21: 0 | S21: 0.1
B22: VGT | C22: 0 | M22: VGT | N22: 0.0999999 | Q22: SPY | R22: 0.25 | S22: 0.4
B23: VNQ | C23: 0 | M23: VNQ | N23: 0 | Q23: JPM | R23: 0 | S23: 0.15
B24: VXUS | C24: 0 | M24: VXUS | N24: 0.05 | Q24: NVDA | R24: 0 | S24: 0.15
Q25: PG | R25: 0 | S25: 0.1
Q26: TLT | R26: 0 | S26: 0.2
Q27: VGT | R27: 0 | S27: 0.15
Q28: VNQ | R28: 0 | S28: 0.15
Q29: VXUS | R29: 0.05 | S29: 0.2

Sheet Rate_Sensitivity
B2: Portfolio Performance Under Different Interest Rate Scenarios
B3: Scenario | C3: Risk-Free Rate | D3: Expected Return | E3: Volatility | F3: Sharpe
B4: Low | C4: 0.02 | D4: 0.21181041 | E4: 0.14677321 | F4: 1.306849
B5: Base | C5: 0.04 | D5: 0.21181041 | E5: 0.14677321 | F5: 1.1705843
B6: High | C6: 0.06 | D6: 0.21834767 | E6: 0.15285654 | F6: 1.0359234
B11: Asset Allocation by Interest Rate Scenario
B12: Asset | C12: Low (2%) | D12: Base (4%) | E12: High (6%)
B13: GLD | C13: 0.2 | D13: 0.2 | E13: 0.2
B14: XOM | C14: 0 | D14: 0 | E14: 0
B15: SPY | C15: 0.25 | D15: 0.25 | E15: 0.25
B16: JPM | C16: 0.15 | D16: 0.15 | E16: 0.15
B17: NVDA | C17: 0.15 | D17: 0.15 | E17: 0.15
B18: PG | C18: 0.1 | D18: 0.1 | E18: 0.052728608
B19: TLT | C19: 0 | D19: 0 | E19: 0
B20: VGT | C20: 0.1 | D20: 0.1 | E20: 0.14727139
B21: VNQ | C21: 0 | D21: 0 | E21: 0
B22: VXUS | C22: 0.05 | D22: 0.05 | E22: 0.05

Sheet Out_of_Sample
B2: Split Configuration | I2: Portfolio Monthly Performance | N2: Portfolio Annualized Performance | T2: Monthly RF | U2: =0.04/12 -> 0.0033333333
B3: Train % | C3: Test % | I3: Metric | J3: Train | K3: Test | N3: Metric | O3: Train | P3: Test | T3: Annual RF | U3: 0.04
B4: 0.7 | C4: 0.3 | I4: Avg Return | J4: =AVERAGEIF($C$19:$C$1000,"Train",$D$19:$D$1000) -> 0.012734211 | K4: =AVERAGEIF($C$19:$C$1000,"Test",$D$19:$D$1000) -> 0.029175146 | N4: Expected Return | O4: =(1+J4)^12-1 -> 0.16398069 | P4: =(1+K4)^12-1 -> 0.41211959
I5: Volatility | J5: {=_xlfn.STDEV.S(IF($C$19:$C$1000="Train",$D$19:$D$1000))} -> 0.043613499 | K5: {=_xlfn.STDEV.S(IF($C$19:$C$1000="Test",$D$19:$D$1000))} -> 0.039352199 | N5: Volatility | O5: =J5*SQRT(12) -> 0.15108159 | P5: =K5*SQRT(12) -> 0.13632001
I6: Sharpe | J6: =(J4-$U$2)/J5 -> 0.21554973 | K6: =(K4-$U$2)/K5 -> 0.65668028 | N6: Sharpe | O6: =J6*SQRT(12) -> 0.74668616 | P6: =K6*SQRT(12) -> 2.2748072
B7: Data Summary | T7: Out-of-Sample Excess Performance (Portfolio vs SPY – Test Period) | AA7: Information Ratio
B8: Observations | C8: =ROWS(Table_RawData[Date]) -> 133 | T8: Metric | U8: Portfolio | V8: SPY | W8: Excess | AA8: =B159/B162 -> 0.71552933
B9: Train | C9: =ROUND(C8*B4,0) -> 93 | I9: SPY Monthly Performance | N9: SPY Annual Performance | T9: Expected Return | U9: =P4 -> 0.41211959 | V9: =P11 -> 0.22885977 | W9: =U9-V9 -> 0.18325981
B10: Test | C10: =C8-C9 -> 40 | I10: Metric | J10: Train | K10: Test | N10: Metric | O10: Train | P10: Test | T10: Volatility | U10: =P5 -> 0.13632001 | V10: =P12 -> 0.12837572 | W10: =U10-V10 -> 0.0079442981
B11: Train End Date | C11: =INDEX(Table_RawData[Date],Out_of_Sample!C9) -> 44805 | I11: Avg Return | J11: =AVERAGEIF($C$19:$C$1000,"Train",$E$19:$E$1000) -> 0.0073986602 | K11: =AVERAGEIF($C$19:$C$1000,"Test",$E$19:$E$1000) -> 0.017322213 | N11: Expected Return | O11: =(1+J11)^12-1 -> 0.092487376 | P11: =(1+K11)^12-1 -> 0.22885977 | T11: Sharpe | U11: =P6 -> 2.2748072 | V11: =P13 -> 1.4711487 | W11: =U11-V11 -> 0.80365848
B12: Test Start Date | C12: =INDEX(Table_RawData[Date],Out_of_Sample!C9+1) -> 44835 | I12: Volatility | J12: {=_xlfn.STDEV.S(IF($C$19:$C$1000="Train",$E$19:$E$1000))} -> 0.045790551 | K12: {=_xlfn.STDEV.S(IF($C$19:$C$1000="Test",$E$19:$E$1000))} -> 0.037058877 | N12: Volatility | O12: =J12*SQRT(12) -> 0.15862312 | P12: =K12*SQRT(12) -> 0.12837572
I13: Sharpe | J13: =(J11-$U$2)/J12 -> 0.088780912 | K13: =(K11-$U$2)/K12 -> 0.37747716 | N13: Sharpe | O13: =(O11-U3)/O12 -> 0.3308936 | P13: =(P11-U3)/P12 -> 1.4711487
B17: Date | C17: Split | D17: Portfolio Return | E17: SPY Return | F17: Portfolio Cumulative | G17: SPY Cumulative | H17: Portfolio Cum (Train) | I17: Portfolio Cum (Test) | J17: Excess Return
C18: =IF(B18="","",IF(B18<=$C$11,"Train","Test"))
B19: =IFERROR(INDEX(Table_RawData[Date], ROWS($B$18:B19)), "") -> 42036 | C19: =IF(B19="","",IF(B19<=$C$11,"Train","Test")) -> Train | D19: {=MMULT( INDEX(Returns!$B$3:$K$1000, MATCH($B19, Returns!$A$3:$A$1000, 0), 0), Solver_Optimization!$C$28:$C$37 )} -> 0.053187884 | E19: =INDEX(Returns!$D$3:$D$1000, MATCH($B19, Returns!$A$3:$A$1000, 0)) -> 0.056204563 | F19: =1*(1+D19) -> 1.0531879 | G19: =1*(1+E19) -> 1.0562046 | H19: =IF($C19="Train",$F19,NA()) -> 1.0531879 | I19: =IF($C19="Test",$F19,NA()) -> #N/A | J19: =D19-E19 -> -0.0030166788
B20: =IFERROR(INDEX(Table_RawData[Date], ROWS($B$18:B20)), "") -> 42064 | C20: =IF(B20="","",IF(B20<=$C$11,"Train","Test")) -> Train | D20: {=MMULT( INDEX(Returns!$B$3:$K$1000, MATCH($B20, Returns!$A$3:$A$1000, 0), 0), Solver_Optimization!$C$28:$C$37 )} -> -0.026987598 | E20: =INDEX(Returns!$D$3:$D$1000, MATCH($B20, Returns!$A$3:$A$1000, 0)) -> -0.020079749 | F20: =F19*(1+D20) -> 1.0247649 | G20: =G19*(1+E20) -> 1.0349962 | H20: =IF($C20="Train",$F20,NA()) -> 1.0247649 | I20: =IF($C20="Test",$F20,NA()) -> #N/A | J20: =D20-E20 -> -0.0069078491
B21: =IFERROR(INDEX(Table_RawData[Date], ROWS($B$18:B21)), "") -> 42095 | C21: =IF(B21="","",IF(B21<=$C$11,"Train","Test")) -> Train | D21: {=MMULT( INDEX(Returns!$B$3:$K$1000, MATCH($B21, Returns!$A$3:$A$1000, 0), 0), Solver_Optimization!$C$28:$C$37 )} -> 0.016568687 | E21: =INDEX(Returns!$D$3:$D$1000, MATCH($B21, Returns!$A$3:$A$1000, 0)) -> 0.009833842 | F21: =F20*(1+D21) -> 1.0417439 | G21: =G20*(1+E21) -> 1.0451742 | H21: =IF($C21="Train",$F21,NA()) -> 1.0417439 | I21: =IF($C21="Test",$F21,NA()) -> #N/A | J21: =D21-E21 -> 0.0067348449
B22: =IFERROR(INDEX(Table_RawData[Date], ROWS($B$18:B22)), "") -> 42125 | C22: =IF(B22="","",IF(B22<=$C$11,"Train","Test")) -> Train | D22: {=MMULT( INDEX(Returns!$B$3:$K$1000, MATCH($B22, Returns!$A$3:$A$1000, 0), 0), Solver_Optimization!$C$28:$C$37 )} -> 0.01018452 | E22: =INDEX(Returns!$D$3:$D$1000, MATCH($B22, Returns!$A$3:$A$1000, 0)) -> 0.012856183 | F22: =F21*(1+D22) -> 1.0523535 | G22: =G21*(1+E22) -> 1.0586112 | H22: =IF($C22="Train",$F22,NA()) -> 1.0523535 | I22: =IF($C22="Test",$F22,NA()) -> #N/A | J22: =D22-E22 -> -0.0026716634
B23: =IFERROR(INDEX(Table_RawData[Date], ROWS($B$18:B23)), "") -> 42156 | C23: =IF(B23="","",IF(B23<=$C$11,"Train","Test")) -> Train | D23: {=MMULT( INDEX(Returns!$B$3:$K$1000, MATCH($B23, Returns!$A$3:$A$1000, 0), 0), Solver_Optimization!$C$28:$C$37 )} -> -0.027888594 | E23: =INDEX(Returns!$D$3:$D$1000, MATCH($B23, Returns!$A$3:$A$1000, 0)) -> -0.025054466 | F23: =F22*(1+D23) -> 1.0230049 | G23: =G22*(1+E23) -> 1.0320882 | H23: =IF($C23="Train",$F23,NA()) -> 1.0230049 | I23: =IF($C23="Test",$F23,NA()) -> #N/A | J23: =D23-E23 -> -0.0028341278
B24: =IFERROR(INDEX(Table_RawData[Date], ROWS($B$18:B24)), "") -> 42186 | C24: =IF(B24="","",IF(B24<=$C$11,"Train","Test")) -> Train | D24: {=MMULT( INDEX(Returns!$B$3:$K$1000, MATCH($B24, Returns!$A$3:$A$1000, 0), 0), Solver_Optimization!$C$28:$C$37 )} -> -0.0053017621 | E24: =INDEX(Returns!$D$3:$D$1000, MATCH($B24, Returns!$A$3:$A$1000, 0)) -> 0.022589264 | F24: =F23*(1+D24) -> 1.0175812 | G24: =G23*(1+E24) -> 1.0554024 | H24: =IF($C24="Train",$F24,NA()) -> 1.0175812 | I24: =IF($C24="Test",$F24,NA()) -> #N/A | J24: =D24-E24 -> -0.027891026
B25: =IFERROR(INDEX(Table_RawData[Date], ROWS($B$18:B25)), "") -> 42217 | C25: =IF(B25="","",IF(B25<=$C$11,"Train","Test")) -> Train | D25: {=MMULT( INDEX(Returns!$B$3:$K$1000, MATCH($B25, Returns!$A$3:$A$1000, 0), 0), Solver_Optimization!$C$28:$C$37 )} -> -0.016563922 | E25: =INDEX(Returns!$D$3:$D$1000, MATCH($B25, Returns!$A$3:$A$1000, 0)) -> -0.060950119 | F25: =F24*(1+D25) -> 1.000726 | G25: =G24*(1+E25) -> 0.99107546 | H25: =IF($C25="Train",$F25,NA()) -> 1.000726 | I25: =IF($C25="Test",$F25,NA()) -> #N/A | J25: =D25-E25 -> 0.044386197
B26: =IFERROR(INDEX(Table_RawData[Date], ROWS($B$18:B26)), "") -> 42248 | C26: =IF(B26="","",IF(B26<=$C$11,"Train","Test")) -> Train | D26: {=MMULT( INDEX(Returns!$B$3:$K$1000, MATCH($B26, Returns!$A$3:$A$1000, 0), 0), Solver_Optimization!$C$28:$C$37 )} -> -0.0038547198 | E26: =INDEX(Returns!$D$3:$D$1000, MATCH($B26, Returns!$A$3:$A$1000, 0)) -> -0.030555977 | F26: =F25*(1+D26) -> 0.9968685 | G26: =G25*(1+E26) -> 0.96079218 | H26: =IF($C26="Train",$F26,NA()) -> 0.9968685 | I26: =IF($C26="Test",$F26,NA()) -> #N/A | J26: =D26-E26 -> 0.026701257
B27: =IFERROR(INDEX(Table_RawData[Date], ROWS($B$18:B27)), "") -> 42278 | C27: =IF(B27="","",IF(B27<=$C$11,"Train","Test")) -> Train | D27: {=MMULT( INDEX(Returns!$B$3:$K$1000, MATCH($B27, Returns!$A$3:$A$1000, 0), 0), Solver_Optimization!$C$28:$C$37 )} -> 0.077972359 | E27: =INDEX(Returns!$D$3:$D$1000, MATCH($B27, Returns!$A$3:$A$1000, 0)) -> 0.085059751 | F27: =F26*(1+D27) -> 1.0745967 | G27: =G26*(1+E27) -> 1.0425169 | H27: =IF($C27="Train",$F27,NA()) -> 1.0745967 | I27: =IF($C27="Test",$F27,NA()) -> #N/A | J27: =D27-E27 -> -0.0070873917
B28: =IFERROR(INDEX(Table_RawData[Date], ROWS($B$18:B28)), "") -> 42309 | C28: =IF(B28="","",IF(B28<=$C$11,"Train","Test")) -> Train | D28: {=MMULT( INDEX(Returns!$B$3:$K$1000, MATCH($B28, Returns!$A$3:$A$1000, 0), 0), Solver_Optimization!$C$28:$C$37 )} -> 0.0071975376 | E28: =INDEX(Returns!$D$3:$D$1000, MATCH($B28, Returns!$A$3:$A$1000, 0)) -> 0.0036550762 | F28: =F27*(1+D28) -> 1.0823311 | G28: =G27*(1+E28) -> 1.0463274 | H28: =IF($C28="Train",$F28,NA()) -> 1.0823311 | I28: =IF($C28="Test",$F28,NA()) -> #N/A | J28: =D28-E28 -> 0.0035424614
B29: =IFERROR(INDEX(Table_RawData[Date], ROWS($B$18:B29)), "") -> 42339 | C29: =IF(B29="","",IF(B29<=$C$11,"Train","Test")) -> Train | D29: {=MMULT( INDEX(Returns!$B$3:$K$1000, MATCH($B29, Returns!$A$3:$A$1000, 0), 0), Solver_Optimization!$C$28:$C$37 )} -> -0.0019826405 | E29: =INDEX(Returns!$D$3:$D$1000, MATCH($B29, Returns!$A$3:$A$1000, 0)) -> -0.023096459 | F29: =F28*(1+D29) -> 1.0801853 | G29: =G28*(1+E29) -> 1.0221609 | H29: =IF($C29="Train",$F29,NA()) -> 1.0801853 | I29: =IF($C29="Test",$F29,NA()) -> #N/A | J29: =D29-E29 -> 0.021113818
B30: =IFERROR(INDEX(Table_RawData[Date], ROWS($B$18:B30)), "") -> 42370 | C30: =IF(B30="","",IF(B30<=$C$11,"Train","Test")) -> Train | D30: {=MMULT( INDEX(Returns!$B$3:$K$1000, MATCH($B30, Returns!$A$3:$A$1000, 0), 0), Solver_Optimization!$C$28:$C$37 )} -> -0.036642688 | E30: =INDEX(Returns!$D$3:$D$1000, MATCH($B30, Returns!$A$3:$A$1000, 0)) -> -0.049786629 | F30: =F29*(1+D30) -> 1.0406044 | G30: =G29*(1+E30) -> 0.971271 | H30: =IF($C30="Train",$F30,NA()) -> 1.0406044 | I30: =IF($C30="Test",$F30,NA()) -> #N/A | J30: =D30-E30 -> 0.01314394
B31: =IFERROR(INDEX(Table_RawData[Date], ROWS($B$18:B31)), "") -> 42401 | C31: =IF(B31="","",IF(B31<=$C$11,"Train","Test")) -> Train | D31: {=MMULT( INDEX(Returns!$B$3:$K$1000, MATCH($B31, Returns!$A$3:$A$1000, 0), 0), Solver_Optimization!$C$28:$C$37 )} -> 0.022148392 | E31: =INDEX(Returns!$D$3:$D$1000, MATCH($B31, Returns!$A$3:$A$1000, 0)) -> -0.00082593434 | F31: =F30*(1+D31) -> 1.0636521 | G31: =G30*(1+E31) -> 0.97046879 | H31: =IF($C31="Train",$F31,NA()) -> 1.0636521 | I31: =IF($C31="Test",$F31,NA()) -> #N/A | J31: =D31-E31 -> 0.022974327
... B150: =IFERROR(INDEX(Table_RawData[Date], ROWS($B$18:B150)), "") -> 46023 | C150: =IF(B150="","",IF(B150<=$C$11,"Train","Test")) -> Test | D150: {=MMULT( INDEX(Returns!$B$3:$K$1000, MATCH($B150, Returns!$A$3:$A$1000, 0), 0), Solver_Optimization!$C$28:$C$37 )} -> 0.020375896 | E150: =INDEX(Returns!$D$3:$D$1000, MATCH($B150, Returns!$A$3:$A$1000, 0)) -> 0.0142832 | F150: =F149*(1+D150) -> 9.0225445 | G150: =G149*(1+E150) -> 3.4678366 | H150: =IF($C150="Train",$F150,NA()) -> #N/A | I150: =IF($C150="Test",$F150,NA()) -> 9.0225445 | J150: =D150-E150 -> 0.0060926958
B158: Excess Return
B159: =AVERAGE(J111:J150) -> 0.011852933
B161: Tracking Error
B162: =_xlfn.STDEV.S(J111:J150) -> 0.016565265

Sheet capm-reg
A1: SUMMARY OUTPUT
A3: Regression Statistics
A4: Multiple R | B4: 0.9077214
A5: R Square | B5: 0.82395813
A6: Adjusted R Square | B6: 0.81932545
A7: Standard Error | B7: 0.016726978
A8: Observations | B8: 40
A10: ANOVA
B11: df | C11: SS | D11: MS | E11: F | F11: Significance F
A12: Regression | B12: 1 | C12: 0.049763138 | D12: 0.049763138 | E12: 177.85774 | F12: 6.5411044e-16
A13: Residual | B13: 38 | C13: 0.010632088 | D13: 0.0002797918
A14: Total | B14: 39 | C14: 0.060395226
B16: Coefficients | C16: Standard Error | D16: t Stat | E16: P-value | F16: Lower 95% | G16: Upper 95% | H16: Lower 95.0% | I16: Upper 95.0%
A17: Intercept | B17: 0.012358014 | C17: 0.0028314364 | D17: 4.3645742 | E17: 9.4390618e-05 | F17: 0.0066260711 | G17: 0.018089958 | H17: 0.0066260711 | I17: 0.018089958
A18: SPY Excess Return | B18: 0.96389409 | C18: 0.072275804 | D18: 13.336332 | E18: 6.5411044e-16 | F18: 0.81757937 | G18: 1.1102088 | H18: 0.81757937 | I18: 1.1102088

Sheet CAPM
B2: CAPM Regression Data – Test Period (Oct 2022 – Jan 2026)
B3: Date | C3: Portfolio Return | D3: SPY Return | E3: RF | F3: Portfolio Excess Return | G3: SPY Excess Return | H3: CAPM Expected Return
B4: =Out_of_Sample!B111 -> 44835 | C4: =Out_of_Sample!D111 -> 0.073528058 | D4: =Out_of_Sample!E111 -> 0.081275547 | E4: =Out_of_Sample!$U$2 -> 0.0033333333 | F4: =C4-E4 -> 0.070194725 | G4: =D4-E4 -> 0.077942214 | H4: =$L$6+$L$7*G4 -> 0.087486054 | K4: CAPM Regression Coefficients | Q4: CAPM Alpha
B5: =Out_of_Sample!B112 -> 44866 | C5: =Out_of_Sample!D112 -> 0.10398928 | D5: =Out_of_Sample!E112 -> 0.055591518 | E5: =Out_of_Sample!$U$2 -> 0.0033333333 | F5: =C5-E5 -> 0.10065595 | G5: =D5-E5 -> 0.052258184 | H5: =$L$6+$L$7*G5 -> 0.062729369 | K5: Variable | L5: Coefficient | M5: t-stat | N5: p-value | Q5: Metric | R5: Value
B6: =Out_of_Sample!B113 -> 44896 | C6: =Out_of_Sample!D113 -> -0.045408132 | D6: =Out_of_Sample!E113 -> -0.061935832 | E6: =Out_of_Sample!$U$2 -> 0.0033333333 | F6: =C6-E6 -> -0.048741466 | G6: =D6-E6 -> -0.065269165 | H6: =$L$6+$L$7*G6 -> -0.050554548 | K6: Intercept | L6: ='capm-reg'!B17 -> 0.012358014 | M6: ='capm-reg'!D17 -> 4.3645742 | N6: ='capm-reg'!E17 -> 9.4390618e-05 | Q6: Monthly Alpha | R6: =L6 -> 0.012358014
B7: =Out_of_Sample!B114 -> 44927 | C7: =Out_of_Sample!D114 -> 0.095053907 | D7: =Out_of_Sample!E114 -> 0.062887326 | E7: =Out_of_Sample!$U$2 -> 0.0033333333 | F7: =C7-E7 -> 0.091720574 | G7: =D7-E7 -> 0.059553992 | H7: =$L$6+$L$7*G7 -> 0.069761756 | K7: SPY Excess Return | L7: ='capm-reg'!B18 -> 0.96389409 | M7: ='capm-reg'!D18 -> 13.336332 | N7: ='capm-reg'!E18 -> 6.5411044e-16 | Q7: Annualized Alpha | R7: =(1 +R6)^12 - 1 -> 0.15880272
B8: =Out_of_Sample!B115 -> 44958 | C8: =Out_of_Sample!D115 -> 0.0088757522 | D8: =Out_of_Sample!E115 -> -0.025142688 | E8: =Out_of_Sample!$U$2 -> 0.0033333333 | F8: =C8-E8 -> 0.0055424189 | G8: =D8-E8 -> -0.028476022 | H8: =$L$6+$L$7*G8 -> -0.015089854
B9: =Out_of_Sample!B116 -> 44986 | C9: =Out_of_Sample!D116 -> 0.068075396 | D9: =Out_of_Sample!E116 -> 0.03313481 | E9: =Out_of_Sample!$U$2 -> 0.0033333333 | F9: =C9-E9 -> 0.064742063 | G9: =D9-E9 -> 0.029801477 | H9: =$L$6+$L$7*G9 -> 0.041083482
B10: =Out_of_Sample!B117 -> 45017 | C10: =Out_of_Sample!D117 -> 0.017323703 | D10: =Out_of_Sample!E117 -> 0.015974987 | E10: =Out_of_Sample!$U$2 -> 0.0033333333 | F10: =C10-E10 -> 0.01399037 | G10: =D10-E10 -> 0.012641654 | H10: =$L$6+$L$7*G10 -> 0.02454323
B11: =Out_of_Sample!B118 -> 45047 | C11: =Out_of_Sample!D118 -> 0.053190694 | D11: =Out_of_Sample!E118 -> 0.0046161614 | E11: =Out_of_Sample!$U$2 -> 0.0033333333 | F11: =C11-E11 -> 0.049857361 | G11: =D11-E11 -> 0.001282828 | H11: =$L$6+$L$7*G11 -> 0.013594525
B12: =Out_of_Sample!B119 -> 45078 | C12: =Out_of_Sample!D119 -> 0.052904203 | D12: =Out_of_Sample!E119 -> 0.06085916 | E12: =Out_of_Sample!$U$2 -> 0.0033333333 | F12: =C12-E12 -> 0.04957087 | G12: =D12-E12 -> 0.057525827 | H12: =$L$6+$L$7*G12 -> 0.067806819 | K12: CAPM Model Summary
B13: =Out_of_Sample!B120 -> 45108 | C13: =Out_of_Sample!D120 -> 0.046318448 | D13: =Out_of_Sample!E120 -> 0.032733261 | E13: =Out_of_Sample!$U$2 -> 0.0033333333 | F13: =C13-E13 -> 0.042985115 | G13: =D13-E13 -> 0.029399928 | H13: =$L$6+$L$7*G13 -> 0.040696431 | K13: Metric | L13: Value
B14: =Out_of_Sample!B121 -> 45139 | C14: =Out_of_Sample!D121 -> -0.012297172 | D14: =Out_of_Sample!E121 -> -0.016251993 | E14: =Out_of_Sample!$U$2 -> 0.0033333333 | F14: =C14-E14 -> -0.015630506 | G14: =D14-E14 -> -0.019585327 | H14: =$L$6+$L$7*G14 -> -0.006520166 | K14: Correlation | L14: ='capm-reg'!B4 -> 0.9077214
B15: =Out_of_Sample!B122 -> 45170 | C15: =Out_of_Sample!D122 -> -0.058452856 | D15: =Out_of_Sample!E122 -> -0.050782725 | E15: =Out_of_Sample!$U$2 -> 0.0033333333 | F15: =C15-E15 -> -0.06178619 | G15: =D15-E15 -> -0.054116058 | H15: =$L$6+$L$7*G15 -> -0.039804134 | K15: R² | L15: ='capm-reg'!B5 -> 0.82395813
B16: =Out_of_Sample!B123 -> 45200 | C16: =Out_of_Sample!D123 -> -0.0055610114 | D16: =Out_of_Sample!E123 -> -0.021708618 | E16: =Out_of_Sample!$U$2 -> 0.0033333333 | F16: =C16-E16 -> -0.0088943447 | G16: =D16-E16 -> -0.025041951 | H16: =$L$6+$L$7*G16 -> -0.011779774 | K16: F-statistic | L16: ='capm-reg'!E12 -> 177.85774
B17: =Out_of_Sample!B124 -> 45231 | C17: =Out_of_Sample!D124 -> 0.088562694 | D17: =Out_of_Sample!E124 -> 0.091343855 | E17: =Out_of_Sample!$U$2 -> 0.0033333333 | F17: =C17-E17 -> 0.085229361 | G17: =D17-E17 -> 0.088010521 | H17: =$L$6+$L$7*G17 -> 0.097190835 | K17: Significance F | L17: ='capm-reg'!F12 -> 6.5411044e-16
B18: =Out_of_Sample!B125 -> 45261 | C18: =Out_of_Sample!D125 -> 0.03507931 | D18: =Out_of_Sample!E125 -> 0.041432954 | E18: =Out_of_Sample!$U$2 -> 0.0033333333 | F18: =C18-E18 -> 0.031745976 | G18: =D18-E18 -> 0.03809962 | H18: =$L$6+$L$7*G18 -> 0.049082013 | K18: Standard Error | L18: 0.016726978
B19: =Out_of_Sample!B126 -> 45292 | C19: =Out_of_Sample!D126 -> 0.049470391 | D19: =Out_of_Sample!E126 -> 0.015926448 | E19: =Out_of_Sample!$U$2 -> 0.0033333333 | F19: =C19-E19 -> 0.046137057 | G19: =D19-E19 -> 0.012593115 | H19: =$L$6+$L$7*G19 -> 0.024496443 | K19: Observations | L19: 40
B20: =Out_of_Sample!B127 -> 45323 | C20: =Out_of_Sample!D127 -> 0.073381542 | D20: =Out_of_Sample!E127 -> 0.052186879 | E20: =Out_of_Sample!$U$2 -> 0.0033333333 | F20: =C20-E20 -> 0.070048209 | G20: =D20-E20 -> 0.048853545 | H20: =$L$6+$L$7*G20 -> 0.059447658
B21: =Out_of_Sample!B128 -> 45352 | C21: =Out_of_Sample!D128 -> 0.059101174 | D21: =Out_of_Sample!E128 -> 0.029503228 | E21: =Out_of_Sample!$U$2 -> 0.0033333333 | F21: =C21-E21 -> 0.05576784 | G21: =D21-E21 -> 0.026169895 | H21: =$L$6+$L$7*G21 -> 0.037583021
B22: =Out_of_Sample!B129 -> 45383 | C22: =Out_of_Sample!D129 -> -0.023994202 | D22: =Out_of_Sample!E129 -> -0.040319651 | E22: =Out_of_Sample!$U$2 -> 0.0033333333 | F22: =C22-E22 -> -0.027327535 | G22: =D22-E22 -> -0.043652985 | H22: =$L$6+$L$7*G22 -> -0.029718839
B23: =Out_of_Sample!B130 -> 45413 | C23: =Out_of_Sample!D130 -> 0.076816595 | D23: =Out_of_Sample!E130 -> 0.050579704 | E23: =Out_of_Sample!$U$2 -> 0.0033333333 | F23: =C23-E23 -> 0.073483261 | G23: =D23-E23 -> 0.047246371 | H23: =$L$6+$L$7*G23 -> 0.057898512
B24: =Out_of_Sample!B131 -> 45444 | C24: =Out_of_Sample!D131 -> 0.037786008 | D24: =Out_of_Sample!E131 -> 0.031951002 | E24: =Out_of_Sample!$U$2 -> 0.0033333333 | F24: =C24-E24 -> 0.034452674 | G24: =D24-E24 -> 0.028617669 | H24: =$L$6+$L$7*G24 -> 0.039942416
B25: =Out_of_Sample!B132 -> 45474 | C25: =Out_of_Sample!D132 -> 0.0076118953 | D25: =Out_of_Sample!E132 -> 0.012109074 | E25: =Out_of_Sample!$U$2 -> 0.0033333333 | F25: =C25-E25 -> 0.004278562 | G25: =D25-E25 -> 0.0087757402 | H25: =$L$6+$L$7*G25 -> 0.020816899
B26: =Out_of_Sample!B133 -> 45505 | C26: =Out_of_Sample!D133 -> 0.028160815 | D26: =Out_of_Sample!E133 -> 0.023365589 | E26: =Out_of_Sample!$U$2 -> 0.0033333333 | F26: =C26-E26 -> 0.024827481 | G26: =D26-E26 -> 0.020032256 | H26: =$L$6+$L$7*G26 -> 0.031666987
B27: =Out_of_Sample!B134 -> 45536 | C27: =Out_of_Sample!D134 -> 0.016376855 | D27: =Out_of_Sample!E134 -> 0.017882487 | E27: =Out_of_Sample!$U$2 -> 0.0033333333 | F27: =C27-E27 -> 0.013043521 | G27: =D27-E27 -> 0.014549153 | H27: =$L$6+$L$7*G27 -> 0.026381857
B28: =Out_of_Sample!B135 -> 45566 | C28: =Out_of_Sample!D135 -> 0.017653465 | D28: =Out_of_Sample!E135 -> -0.0089235917 | E28: =Out_of_Sample!$U$2 -> 0.0033333333 | F28: =C28-E28 -> 0.014320132 | G28: =D28-E28 -> -0.012256925 | H28: =$L$6+$L$7*G28 -> 0.00054363689
B29: =Out_of_Sample!B136 -> 45597 | C29: =Out_of_Sample!D136 -> 0.046092008 | D29: =Out_of_Sample!E136 -> 0.059633512 | E29: =Out_of_Sample!$U$2 -> 0.0033333333 | F29: =C29-E29 -> 0.042758674 | G29: =D29-E29 -> 0.056300178 | H29: =$L$6+$L$7*G29 -> 0.066625423
B30: =Out_of_Sample!B137 -> 45627 | C30: =Out_of_Sample!D137 -> -0.026793791 | D30: =Out_of_Sample!E137 -> -0.027333831 | E30: =Out_of_Sample!$U$2 -> 0.0033333333 | F30: =C30-E30 -> -0.030127124 | G30: =D30-E30 -> -0.030667165 | H30: =$L$6+$L$7*G30 -> -0.017201884
B31: =Out_of_Sample!B138 -> 45658 | C31: =Out_of_Sample!D138 -> 0.015357804 | D31: =Out_of_Sample!E138 -> 0.026856402 | E31: =Out_of_Sample!$U$2 -> 0.0033333333 | F31: =C31-E31 -> 0.01202447 | G31: =D31-E31 -> 0.023523069 | H31: =$L$6+$L$7*G31 -> 0.035031761
... B43: =Out_of_Sample!B150 -> 46023 | C43: =Out_of_Sample!D150 -> 0.020375896 | D43: =Out_of_Sample!E150 -> 0.0142832 | E43: =Out_of_Sample!$U$2 -> 0.0033333333 | F43: =C43-E43 -> 0.017042563 | G43: =D43-E43 -> 0.010949867 | H43: =$L$6+$L$7*G43 -> 0.022912527

Sheet Return_Attribution
B3: Asset | C3: Weights | D3: Avg Test Return | E3: Contribution | F3: Contribution %
B4: XOM | C4: 0 | D4: =AVERAGEIFS(Returns!C3:C135,Returns!A3:A135,">="&Out_of_Sample!C12) -> 0.012042723 | E4: =C4*D4 -> 0 | F4: =E4/$E$14 -> 0
B5: TLT | C5: 0 | D5: =AVERAGEIFS(Returns!H3:H135,Returns!A3:A135,">="&Out_of_Sample!C12) -> -0.0029908855 | E5: =C5*D5 -> 0 | F5: =E5/$E$14 -> 0
B6: VNQ | C6: 0 | D6: =AVERAGEIFS(Returns!J3:J135,Returns!A3:A135,">="&Out_of_Sample!C12) -> 0.0042150473 | E6: =C6*D6 -> 0 | F6: =E6/$E$14 -> 0
B7: PG | C7: 0.1 | D7: =AVERAGEIFS(Returns!G3:G135,Returns!A3:A135,">="&Out_of_Sample!C12) -> 0.0055058081 | E7: =C7*D7 -> 0.00055058081 | F7: =E7/$E$14 -> 0.01887157
B8: VXUS | C8: 0.05 | D8: =AVERAGEIFS(Returns!K3:K135,Returns!A3:A135,">="&Out_of_Sample!C12) -> 0.014632642 | E8: =C8*D8 -> 0.00073163208 | F8: =E8/$E$14 -> 0.025077238
B9: JPM | C9: 0.1 | D9: =AVERAGEIFS(Returns!E3:E135,Returns!A3:A135,">="&Out_of_Sample!C12) -> 0.029692213 | E9: =C9*D9 -> 0.0029692214 | F9: =E9/$E$14 -> 0.10177229
B10: VGT | C10: 0.15 | D10: =AVERAGEIFS(Returns!I3:I135,Returns!A3:A135,">="&Out_of_Sample!C12) -> 0.024082006 | E10: =C10*D10 -> 0.0036123009 | F10: =E10/$E$14 -> 0.12381432
B11: SPY | C11: 0.25 | D11: =AVERAGEIFS(Returns!D3:D135,Returns!A3:A135,">="&Out_of_Sample!C12) -> 0.017322213 | E11: =C11*D11 -> 0.0043305533 | F11: =E11/$E$14 -> 0.14843296
B12: GLD | C12: 0.2 | D12: =AVERAGEIFS(Returns!B3:B134,Returns!A3:A134,">="&Out_of_Sample!C12) -> 0.026133536 | E12: =C12*D12 -> 0.0052267073 | F12: =E12/$E$14 -> 0.17914931
B13: NVDA | C13: 0.15 | D13: =AVERAGEIFS(Returns!F3:F135,Returns!A3:A135,">="&Out_of_Sample!C12) -> 0.078361003 | E13: =C13*D13 -> 0.011754151 | F13: =E13/$E$14 -> 0.40288232
E14: =SUM(E4:E13) -> 0.029175146

Sheet Risk_Contribution
A1: Asset | B1: Weight | C1: Monthly Risk Contribution | D1: Risk Contribution (%)
A2: GLD | B2: 0.2 | C2: =($B2*E2)/$B$40 -> 0.0015872266 | D2: =C2/SUM($C$2:$C$11) -> 0.037144492 | E2: {=MMULT('Portfolio '!$B$22:$K$31,$B$2:$B$11)} -> 0.00033912004
A3: XOM | B3: 0 | C3: =($B3*E3)/$B$40 -> 0 | D3: =C3/SUM($C$2:$C$11) -> 0 | E3: 0.0011037774
A4: SPY | B4: 0.25 | C4: =($B4*E4)/$B$40 -> 0.0098871873 | D4: =C4/SUM($C$2:$C$11) -> 0.2313813 | E4: 0.0016899633
A5: JPM | B5: 0.1 | C5: =($B5*E5)/$B$40 -> 0.0042104797 | D5: =C5/SUM($C$2:$C$11) -> 0.098534216 | E5: 0.0017991861
A6: NVDA | B6: 0.15 | C6: =($B6*E6)/$B$40 -> 0.016133696 | D6: =C6/SUM($C$2:$C$11) -> 0.37756294 | E6: 0.0045960752
A7: PG | B7: 0.1 | C7: =($B7*E7)/$B$40 -> 0.0014963074 | D7: =C7/SUM($C$2:$C$11) -> 0.035016789 | E7: 0.00063938926
A8: TLT | B8: 0 | C8: =($B8*E8)/$B$40 -> 0 | D8: =C8/SUM($C$2:$C$11) -> 0 | E8: 0.0003468641
A9: VGT | B9: 0.15 | C9: =($B9*E9)/$B$40 -> 0.0077104432 | D9: =C9/SUM($C$2:$C$11) -> 0.18044084 | E9: 0.002196507
A10: VNQ | B10: 0 | C10: =($B10*E10)/$B$40 -> 0 | D10: =C10/SUM($C$2:$C$11) -> 0 | E10: 0.0013704844
A11: VXUS | B11: 0.05 | C11: =($B11*E11)/$B$40 -> 0.0017058028 | D11: =C11/SUM($C$2:$C$11) -> 0.039919428 | E11: 0.0014578181
A39: Monthly Variance | B39: {=MMULT( MMULT(A46:J46, 'Portfolio '!B22:K31), B2:B11 )} -> 0.0018259506
A40: Monthly Volatility | B40: =SQRT(B39) -> 0.042731143
A45: GLD | B45: XOM | C45: SPY | D45: JPM | E45: NVDA | F45: PG | G45: TLT | H45: VGT | I45: VNQ | J45: VXUS
A46: 0.2 | B46: 0 | C46: 0.25 | D46: 0.1 | E46: 0.15 | F46: 0.1 | G46: 0 | H46: 0.15 | I46: 0 | J46: 0.05

Sheet VaR
B2: Monthly Return | G2: Weights
B3: Date | C3: Portfolio Return | G3: GLD | H3: XOM | I3: SPY | J3: JPM | K3: NVDA | L3: PG | M3: TLT | N3: VGT | O3: VNQ | P3: VXUS
B4: 42036 | C4: =SUMPRODUCT(Returns!B3:K3,$G$4:$P$4) -> 0.053187884 | G4: 0.2 | H4: 0 | I4: 0.25 | J4: 0.1 | K4: 0.15 | L4: 0.1 | M4: 0 | N4: 0.15 | O4: 0 | P4: 0.05
B5: 42064 | C5: =SUMPRODUCT(Returns!B4:K4,$G$4:$P$4) -> -0.026987598
B6: 42095 | C6: =SUMPRODUCT(Returns!B5:K5,$G$4:$P$4) -> 0.016568687 | AA6: Confidence Level | AB6: VaR | AC6: CVaR
B7: 42125 | C7: =SUMPRODUCT(Returns!B6:K6,$G$4:$P$4) -> 0.01018452 | AA7: 0.9 | AB7: -0.037716685 | AC7: -0.065984934
B8: 42156 | C8: =SUMPRODUCT(Returns!B7:K7,$G$4:$P$4) -> -0.027888594 | G8: Portfolio VaR | K8: Portfolio CVaR | AA8: 0.95 | AB8: -0.061948557 | AC8: -0.085289795
B9: 42186 | C9: =SUMPRODUCT(Returns!B8:K8,$G$4:$P$4) -> -0.0053017621 | G9: Metric | H9: Value | K9: Metric | L9: Value | AA9: 0.99 | AB9: -0.095452237 | AC9: -0.099893073
B10: 42217 | C10: =SUMPRODUCT(Returns!B9:K9,$G$4:$P$4) -> -0.016563922 | G10: VaR 90% | H10: =_xlfn.PERCENTILE.INC(C4:C135, 0.1) -> -0.036517951 | K10: CVaR 90% | L10: =AVERAGEIF($C$4:$C$1000,"<="&_xlfn.PERCENTILE.INC($C$4:$C$1000,0.1),$C$4:$C$1000) -> -0.066254302
B11: 42248 | C11: =SUMPRODUCT(Returns!B10:K10,$G$4:$P$4) -> -0.0038547198 | G11: VaR 95% | H11: =_xlfn.PERCENTILE.INC(C4:C135, 0.05) -> -0.063572661 | K11: CVaR 95% | L11: =AVERAGEIF($C$4:$C$1000,"<="&_xlfn.PERCENTILE.INC($C$4:$C$1000,0.05),$C$4:$C$1000) -> -0.084363775
B12: 42278 | C12: =SUMPRODUCT(Returns!B11:K11,$G$4:$P$4) -> 0.077972359 | G12: VaR 99% | H12: =_xlfn.PERCENTILE.INC(C4:C135, 0.01) -> -0.095975142 | K12: CVaR 99% | L12: =AVERAGEIF($C$4:$C$1000,"<="&_xlfn.PERCENTILE.INC($C$4:$C$1000,0.01),$C$4:$C$1000) -> -0.10071168
B13: 42309 | C13: =SUMPRODUCT(Returns!B12:K12,$G$4:$P$4) -> 0.0071975376
B14: 42339 | C14: =SUMPRODUCT(Returns!B13:K13,$G$4:$P$4) -> -0.0019826405
B15: 42370 | C15: =SUMPRODUCT(Returns!B14:K14,$G$4:$P$4) -> -0.036642688
B16: 42401 | C16: =SUMPRODUCT(Returns!B15:K15,$G$4:$P$4) -> 0.022148392
B17: 42430 | C17: =SUMPRODUCT(Returns!B16:K16,$G$4:$P$4) -> 0.059373255
B18: 42461 | C18: =SUMPRODUCT(Returns!B17:K17,$G$4:$P$4) -> 0.0093308677
B19: 42491 | C19: =SUMPRODUCT(Returns!B18:K18,$G$4:$P$4) -> 0.051117085
B20: 42522 | C20: =SUMPRODUCT(Returns!B19:K19,$G$4:$P$4) -> 0.013452798
B21: 42552 | C21: =SUMPRODUCT(Returns!B20:K20,$G$4:$P$4) -> 0.062529748
B22: 42583 | C22: =SUMPRODUCT(Returns!B21:K21,$G$4:$P$4) -> 0.015532498
B23: 42614 | C23: =SUMPRODUCT(Returns!B22:K22,$G$4:$P$4) -> 0.022931434
B24: 42644 | C24: =SUMPRODUCT(Returns!B23:K23,$G$4:$P$4) -> -0.0051242385
... B26: 42705 | C26: =SUMPRODUCT(Returns!B25:K25,$G$4:$P$4) -> 0.034702609
B27: 42736 | C27: =SUMPRODUCT(Returns!B26:K26,$G$4:$P$4) -> 0.02945269 | Z27: בוצע
B28: 42767 | C28: =SUMPRODUCT(Returns!B27:K27,$G$4:$P$4) -> 0.024870938
B29: 42795 | C29: =SUMPRODUCT(Returns!B28:K28,$G$4:$P$4) -> 0.0088943649
B30: 42826 | C30: =SUMPRODUCT(Returns!B29:K29,$G$4:$P$4) -> 0.00064034801
B31: 42856 | C31: =SUMPRODUCT(Returns!B30:K30,$G$4:$P$4) -> 0.064139756
B32: 42887 | C32: =SUMPRODUCT(Returns!B31:K31,$G$4:$P$4) -> 0.0018111778
B33: 42917 | C33: =SUMPRODUCT(Returns!B32:K32,$G$4:$P$4) -> 0.040993894
B34: 42948 | C34: =SUMPRODUCT(Returns!B33:K33,$G$4:$P$4) -> 0.021316232
B35: 42979 | C35: =SUMPRODUCT(Returns!B34:K34,$G$4:$P$4) -> 0.010290264
B36: 43009 | C36: =SUMPRODUCT(Returns!B35:K35,$G$4:$P$4) -> 0.040230629
B37: 43040 | C37: =SUMPRODUCT(Returns!B36:K36,$G$4:$P$4) -> 0.014065001
B38: 43070 | C38: =SUMPRODUCT(Returns!B37:K37,$G$4:$P$4) -> 0.0052908759
B39: 43101 | C39: =SUMPRODUCT(Returns!B38:K38,$G$4:$P$4) -> 0.077170807
... B135: 46023 | C135: =SUMPRODUCT(Returns!B134:K134,$G$4:$P$4) -> 0.020375896

Sheet Drawdown
B3: Date | C3: Portfolio Return | D3: Cumulative Return | E3: Running Peak | F3: Drawdown | G3: Months Under Water | J3: Metric | K3: Value | L3: Date
B4: 42036 | C4: =VaR!C4 -> 0.053187884 | D4: =1+C4 -> 1.0531879 | E4: =D4 -> 1.0531879 | F4: =(D4/E4)-1 -> 0 | G4: =IF($D4<$E4,1,0) -> 0 | J4: Maximum Drawdown | K4: 0.2941 | L4: 44805
B5: 42064 | C5: =VaR!C5 -> -0.026987598 | D5: =D4*(1+C5) -> 1.0247649 | E5: =MAX(E4,D5) -> 1.0531879 | F5: =(D5/E5)-1 -> -0.026987598 | G5: =IF($D5<$E5,G4+1,0) -> 1 | J5: Recovery Period (Trough → Peak) | K5: 8 Months | L5: 45047
B6: 42095 | C6: =VaR!C6 -> 0.016568687 | D6: =D5*(1+C6) -> 1.0417439 | E6: =MAX(E5,D6) -> 1.0531879 | F6: =(D6/E6)-1 -> -0.010866061 | G6: =IF($D6<$E6,G5+1,0) -> 2 | J6: Max Drawdown Duration (Peak → Peak) | K6: 16 Months | L6: Dec 2021 - May 2023
B7: 42125 | C7: =VaR!C7 -> 0.01018452 | D7: =D6*(1+C7) -> 1.0523535 | E7: =MAX(E6,D7) -> 1.0531879 | F7: =(D7/E7)-1 -> -0.00079220633 | G7: =IF($D7<$E7,G6+1,0) -> 3
B8: 42156 | C8: =VaR!C8 -> -0.027888594 | D8: =D7*(1+C8) -> 1.0230049 | E8: =MAX(E7,D8) -> 1.0531879 | F8: =(D8/E8)-1 -> -0.028658707 | G8: =IF($D8<$E8,G7+1,0) -> 4
B9: 42186 | C9: =VaR!C9 -> -0.0053017621 | D9: =D8*(1+C9) -> 1.0175812 | E9: =MAX(E8,D9) -> 1.0531879 | F9: =(D9/E9)-1 -> -0.033808527 | G9: =IF($D9<$E9,G8+1,0) -> 5
B10: 42217 | C10: =VaR!C10 -> -0.016563922 | D10: =D9*(1+C10) -> 1.000726 | E10: =MAX(E9,D10) -> 1.0531879 | F10: =(D10/E10)-1 -> -0.049812447 | G10: =IF($D10<$E10,G9+1,0) -> 6
B11: 42248 | C11: =VaR!C11 -> -0.0038547198 | D11: =D10*(1+C11) -> 0.9968685 | E11: =MAX(E10,D11) -> 1.0531879 | F11: =(D11/E11)-1 -> -0.053475154 | G11: =IF($D11<$E11,G10+1,0) -> 7
B12: 42278 | C12: =VaR!C12 -> 0.077972359 | D12: =D11*(1+C12) -> 1.0745967 | E12: =MAX(E11,D12) -> 1.0745967 | F12: =(D12/E12)-1 -> 0 | G12: =IF($D12<$E12,G11+1,0) -> 0
B13: 42309 | C13: =VaR!C13 -> 0.0071975376 | D13: =D12*(1+C13) -> 1.0823311 | E13: =MAX(E12,D13) -> 1.0823311 | F13: =(D13/E13)-1 -> 0 | G13: =IF($D13<$E13,G12+1,0) -> 0
B14: 42339 | C14: =VaR!C14 -> -0.0019826405 | D14: =D13*(1+C14) -> 1.0801853 | E14: =MAX(E13,D14) -> 1.0823311 | F14: =(D14/E14)-1 -> -0.0019826405 | G14: =IF($D14<$E14,G13+1,0) -> 1
B15: 42370 | C15: =VaR!C15 -> -0.036642688 | D15: =D14*(1+C15) -> 1.0406044 | E15: =MAX(E14,D15) -> 1.0823311 | F15: =(D15/E15)-1 -> -0.038552679 | G15: =IF($D15<$E15,G14+1,0) -> 2
B16: 42401 | C16: =VaR!C16 -> 0.022148392 | D16: =D15*(1+C16) -> 1.0636521 | E16: =MAX(E15,D16) -> 1.0823311 | F16: =(D16/E16)-1 -> -0.017258167 | G16: =IF($D16<$E16,G15+1,0) -> 3
B17: 42430 | C17: =VaR!C17 -> 0.059373255 | D17: =D16*(1+C17) -> 1.1268046 | E17: =MAX(E16,D17) -> 1.1268046 | F17: =(D17/E17)-1 -> 0 | G17: =IF($D17<$E17,G16+1,0) -> 0
B18: 42461 | C18: =VaR!C18 -> 0.0093308677 | D18: =D17*(1+C18) -> 1.1373186 | E18: =MAX(E17,D18) -> 1.1373186 | F18: =(D18/E18)-1 -> 0 | G18: =IF($D18<$E18,G17+1,0) -> 0
... B135: 46023 | C135: =VaR!C135 -> 0.020375896 | D135: =D134*(1+C135) -> 9.0225445 | E135: =MAX(E134,D135) -> 9.0225445 | F135: =(D135/E135)-1 -> 0 | G135: =IF($D135<$E135,G134+1,0) -> 0
B144: Max DD Row | C144: =MATCH(MIN($F:$F),$F:$F,0) -> 95
B145: Recovery Row | C145: =MATCH(0,F96:F200,0)+95 -> 103
B150: Maximum Drawdown | C150: Max DD date | D150: Recovery Period (Months) | E150: Recovery Date
B151: =-MIN(F4:F135) -> 0.29410803 | C151: =INDEX(B4:B135,MATCH(-B151,F4:F135,0)) -> 44805 | D151: =103-95 -> 8 | E151: =INDEX(B:B,103) -> 45047
B154: Max Recovery Time (Months)
B155: =MAX(G:G) -> 16

Sheet stress_test
B2: Event | C2: Month | D2: Portfolio Return | E2: SPY Return | F2: Excess
B3: COVID Crash | C3: 43891 | D3: =Out_of_Sample!D80 -> -0.085177729 | E3: =Out_of_Sample!E80 -> -0.12998717 | F3: =D3-E3 -> 0.044809445
B4: Inflation Shock | C4: 44713 | D4: =Out_of_Sample!D107 -> -0.089386065 | E4: =Out_of_Sample!E107 -> -0.086406897 | F4: =D4-E4 -> -0.0029791677
B5: AI Rally | C5: 45047 | D5: =Out_of_Sample!D118 -> 0.053190694 | E5: =Out_of_Sample!E118 -> 0.0046161614 | F5: =D5-E5 -> 0.048574533

Sheet Dashboard
B2: Multi-Asset Portfolio Strategy & Performance Analytics
L27: Event | M27: Month | N27: Portfolio Return | O27: SPY Return
L28: COVID Crash | M28: 43891 | N28: -0.085177729 | O28: -0.12998717
L29: Inflation Shock | M29: 44713 | N29: -0.089386065 | O29: -0.086406897
L30: AI Rally | M30: 45047 | N30: 0.053190694 | O30: 0.0046161614
L36: Metric | M36: Initial | N36: Final
L37: Return | M37: 0.1197951 | N37: 0.21259575
L38: Volatility | M38: 0.12609759 | N38: 0.14858893
L39: Sharpe Ratio | M39: 0.63280431 | N39: 1.1615654

Sheet Sheet1
C4: Expected Monthly Return | D4: Expected Annual Return | E4: Monthly Volatility | F4: Annualized Volatility | G4: Sharpe Ratio
C5: =AVERAGE(Out_of_Sample!D19:D150) -> 0.017716313 | D5: =C5*12 -> 0.21259575 | E5: =_xlfn.STDEV.S(Out_of_Sample!D19:D150) -> 0.042893929 | F5: =E5*SQRT(12) -> 0.14858893 | G5: =(D5-0.04)/F5 -> 1.1615654
C9: Metric | D9: Initial | E9: Final
C10: Return | D10: ='Portfolio '!B16 -> 0.1197951 | E10: =D5 -> 0.21259575
C11: Volatility | D11: ='Portfolio '!B39 -> 0.12609759 | E11: =F5 -> 0.14858893
C12: Sharpe Ratio | D12: ='Portfolio '!B40 -> 0.63280431 | E12: =G5 -> 1.1615654
